[
  {
    "train/grad_norm": 5.09375,
    "eval/mean_token_accuracy": null,
    "eval/loss": null,
    "train/num_tokens": 31446,
    "eval/samples_per_second": null,
    "_runtime": 77.744132831,
    "train/epoch": 0.003972194637537239,
    "eval/entropy": null,
    "eval/runtime": null,
    "train/loss": 4.792159557342529,
    "train/mean_token_accuracy": 0.3139912635087967,
    "train/entropy": 1.430586814880371,
    "train/global_step": 1,
    "eval/num_tokens": null,
    "_step": 0,
    "eval/steps_per_second": null,
    "_timestamp": 1774066153.7528596,
    "train/learning_rate": 0
  },
  {
    "_timestamp": 1774066462.1869268,
    "train/mean_token_accuracy": 0.3179510813206434,
    "train/learning_rate": 2.105263157894737e-06,
    "train/num_tokens": 158215,
    "_runtime": 386.178232546,
    "eval/mean_token_accuracy": null,
    "train/epoch": 0.019860973187686197,
    "train/grad_norm": 4.90625,
    "eval/steps_per_second": null,
    "train/loss": 4.695919036865234,
    "train/entropy": 1.4484854713082314,
    "eval/samples_per_second": null,
    "eval/loss": null,
    "eval/entropy": null,
    "eval/runtime": null,
    "train/global_step": 5,
    "eval/num_tokens": null,
    "_step": 1
  },
  {
    "train/epoch": 0.039721946375372394,
    "eval/entropy": null,
    "train/learning_rate": 4.736842105263158e-06,
    "_step": 2,
    "train/grad_norm": 4.5,
    "eval/loss": null,
    "train/num_tokens": 317045,
    "eval/samples_per_second": null,
    "eval/mean_token_accuracy": null,
    "train/mean_token_accuracy": 0.33771234303712844,
    "train/entropy": 1.5536160230636598,
    "eval/num_tokens": null,
    "_runtime": 774.399351985,
    "train/loss": 4.250265502929688,
    "eval/runtime": null,
    "train/global_step": 10,
    "eval/steps_per_second": null,
    "_timestamp": 1774066850.4082122
  },
  {
    "train/num_tokens": 475810,
    "_runtime": 1161.016543493,
    "train/epoch": 0.05958291956305859,
    "eval/loss": null,
    "eval/entropy": null,
    "_step": 3,
    "eval/runtime": null,
    "eval/steps_per_second": null,
    "_timestamp": 1774067237.0254617,
    "eval/mean_token_accuracy": null,
    "train/loss": 3.1896228790283203,
    "train/learning_rate": 7.368421052631579e-06,
    "eval/num_tokens": null,
    "train/grad_norm": 2.546875,
    "train/mean_token_accuracy": 0.4295877322554588,
    "train/entropy": 1.631841242313385,
    "train/global_step": 15,
    "eval/samples_per_second": null
  },
  {
    "eval/runtime": null,
    "train/grad_norm": 1.1875,
    "train/mean_token_accuracy": 0.5094403520226478,
    "train/entropy": 1.663425362110138,
    "train/num_tokens": 633922,
    "eval/num_tokens": null,
    "eval/steps_per_second": null,
    "_timestamp": 1774067622.11943,
    "eval/mean_token_accuracy": null,
    "eval/loss": null,
    "eval/entropy": null,
    "train/learning_rate": 1e-05,
    "train/global_step": 20,
    "eval/samples_per_second": null,
    "_runtime": 1546.110491674,
    "train/epoch": 0.07944389275074479,
    "train/loss": 2.4237171173095704,
    "_step": 4
  },
  {
    "eval/num_tokens": null,
    "_runtime": 1921.960576658,
    "eval/loss": null,
    "train/learning_rate": 1.263157894736842e-05,
    "train/entropy": 1.6169242322444917,
    "train/num_tokens": 789747,
    "eval/samples_per_second": null,
    "eval/steps_per_second": null,
    "eval/mean_token_accuracy": null,
    "train/grad_norm": 0.73828125,
    "eval/entropy": null,
    "eval/runtime": null,
    "_step": 5,
    "_timestamp": 1774067997.969481,
    "train/epoch": 0.09930486593843098,
    "train/loss": 1.7852975845336914,
    "train/mean_token_accuracy": 0.6205967336893081,
    "train/global_step": 25
  },
  {
    "eval/steps_per_second": null,
    "train/epoch": 0.11916583912611718,
    "train/loss": 1.2569653511047363,
    "train/mean_token_accuracy": 0.7309842109680176,
    "train/entropy": 1.2502435863018035,
    "train/num_tokens": 945921,
    "train/global_step": 30,
    "_step": 6,
    "eval/loss": null,
    "eval/entropy": null,
    "train/learning_rate": 1.5263157894736846e-05,
    "eval/num_tokens": null,
    "train/grad_norm": 0.75390625,
    "_runtime": 2300.641545828,
    "eval/runtime": null,
    "_timestamp": 1774068376.6504483,
    "eval/mean_token_accuracy": null,
    "eval/samples_per_second": null
  },
  {
    "train/grad_norm": 0.2197265625,
    "train/epoch": 0.13902681231380337,
    "eval/steps_per_second": null,
    "_timestamp": 1774068753.23888,
    "eval/entropy": null,
    "train/mean_token_accuracy": 0.8209432303905487,
    "_step": 7,
    "_runtime": 2677.229982201,
    "eval/mean_token_accuracy": null,
    "eval/loss": null,
    "train/entropy": 0.787426033616066,
    "train/global_step": 35,
    "eval/num_tokens": null,
    "eval/samples_per_second": null,
    "train/loss": 0.8829351425170898,
    "train/learning_rate": 1.7894736842105264e-05,
    "eval/runtime": null,
    "train/num_tokens": 1101888.0
  },
  {
    "eval/mean_token_accuracy": null,
    "train/learning_rate": 1.999990427614762e-05,
    "train/global_step": 40,
    "_runtime": 3062.723894261,
    "_timestamp": 1774069138.7328014,
    "train/epoch": 0.15888778550148958,
    "eval/loss": null,
    "train/mean_token_accuracy": 0.8338898360729218,
    "train/num_tokens": 1259952.0,
    "eval/num_tokens": null,
    "eval/samples_per_second": null,
    "train/grad_norm": 0.1484375,
    "eval/entropy": null,
    "train/loss": 0.8034293174743652,
    "eval/runtime": null,
    "_step": 8,
    "eval/steps_per_second": null,
    "train/entropy": 0.748714479804039
  },
  {
    "eval/steps_per_second": null,
    "_runtime": 3447.692200557,
    "train/num_tokens": 1417720.0,
    "eval/samples_per_second": null,
    "eval/loss": null,
    "train/learning_rate": 1.9996554133734473e-05,
    "train/entropy": 0.7610264271497726,
    "eval/num_tokens": null,
    "eval/entropy": null,
    "train/loss": 0.7763055324554443,
    "train/mean_token_accuracy": 0.8409307956695556,
    "train/global_step": 45,
    "_step": 9,
    "_timestamp": 1774069523.7010982,
    "eval/mean_token_accuracy": null,
    "train/epoch": 0.17874875868917578,
    "eval/runtime": null,
    "train/grad_norm": 0.1142578125
  },
  {
    "train/epoch": 0.19860973187686196,
    "eval/entropy": null,
    "train/entropy": 0.7559784382581711,
    "eval/samples_per_second": null,
    "_runtime": 3828.479817796,
    "eval/mean_token_accuracy": null,
    "eval/runtime": null,
    "train/global_step": 50,
    "_step": 10,
    "train/loss": 0.7563497066497803,
    "eval/num_tokens": null,
    "eval/steps_per_second": null,
    "eval/loss": null,
    "train/mean_token_accuracy": 0.843366289138794,
    "train/learning_rate": 1.9988419631155686e-05,
    "train/num_tokens": 1574506.0,
    "train/grad_norm": 0.08935546875,
    "_timestamp": 1774069904.488631
  },
  {
    "eval/mean_token_accuracy": null,
    "eval/samples_per_second": null,
    "_step": 11,
    "train/grad_norm": 0.0986328125,
    "_runtime": 4207.014858174,
    "train/loss": 0.7102647304534913,
    "train/mean_token_accuracy": 0.8530440181493759,
    "train/learning_rate": 1.99755046615918e-05,
    "train/entropy": 0.715244859457016,
    "train/num_tokens": 1730683.0,
    "train/global_step": 55,
    "train/epoch": 0.21847070506454816,
    "eval/runtime": null,
    "eval/steps_per_second": null,
    "_timestamp": 1774070283.0237393,
    "eval/loss": null,
    "eval/entropy": null,
    "eval/num_tokens": null
  },
  {
    "train/loss": 0.766968059539795,
    "train/entropy": 0.7809337556362153,
    "train/global_step": 60,
    "eval/loss": null,
    "eval/runtime": null,
    "train/num_tokens": 1887369.0,
    "_runtime": 4586.481619622,
    "eval/mean_token_accuracy": null,
    "train/epoch": 0.23833167825223436,
    "eval/entropy": null,
    "train/mean_token_accuracy": 0.8391595661640168,
    "eval/num_tokens": null,
    "eval/samples_per_second": null,
    "train/grad_norm": 0.08544921875,
    "eval/steps_per_second": null,
    "_timestamp": 1774070662.49055,
    "train/learning_rate": 1.9957815406159344e-05,
    "_step": 12
  },
  {
    "train/grad_norm": 0.083984375,
    "eval/loss": null,
    "train/loss": 0.7785827159881592,
    "train/num_tokens": 2045179.0,
    "train/global_step": 65,
    "eval/num_tokens": null,
    "eval/steps_per_second": null,
    "train/epoch": 0.25819265143992054,
    "eval/entropy": null,
    "train/mean_token_accuracy": 0.8357383489608765,
    "_runtime": 4970.897851868,
    "eval/mean_token_accuracy": null,
    "eval/runtime": null,
    "eval/samples_per_second": null,
    "_timestamp": 1774071046.9067352,
    "train/learning_rate": 1.993536033095252e-05,
    "train/entropy": 0.788267508149147,
    "_step": 13
  },
  {
    "eval/steps_per_second": null,
    "eval/mean_token_accuracy": null,
    "train/epoch": 0.27805362462760674,
    "eval/entropy": null,
    "eval/runtime": null,
    "train/num_tokens": 2203849.0,
    "train/global_step": 70,
    "eval/loss": null,
    "train/mean_token_accuracy": 0.8427329272031784,
    "train/grad_norm": 0.080078125,
    "_runtime": 5359.023175668,
    "_timestamp": 1774071435.032084,
    "train/loss": 0.741574764251709,
    "train/entropy": 0.748163029551506,
    "eval/num_tokens": null,
    "_step": 14,
    "train/learning_rate": 1.9908150182991338e-05,
    "eval/samples_per_second": null
  },
  {
    "train/global_step": 75,
    "_step": 15,
    "eval/steps_per_second": null,
    "_timestamp": 1774071819.1348774,
    "eval/mean_token_accuracy": null,
    "eval/samples_per_second": null,
    "_runtime": 5743.125952598,
    "eval/loss": null,
    "train/mean_token_accuracy": 0.8338169515132904,
    "train/learning_rate": 1.987619798507809e-05,
    "train/entropy": 0.7813745260238647,
    "eval/num_tokens": null,
    "train/grad_norm": 0.07763671875,
    "train/epoch": 0.29791459781529295,
    "eval/entropy": null,
    "train/num_tokens": 2361231.0,
    "train/loss": 0.7753995418548584,
    "eval/runtime": null
  },
  {
    "_runtime": 6127.977358659,
    "train/epoch": 0.31777557100297915,
    "eval/loss": null,
    "train/learning_rate": 1.9839519029564608e-05,
    "eval/runtime": null,
    "eval/steps_per_second": null,
    "eval/entropy": null,
    "train/loss": 0.7205254077911377,
    "train/global_step": 80,
    "eval/samples_per_second": null,
    "_step": 16,
    "train/mean_token_accuracy": 0.8492078751325607,
    "train/entropy": 0.7236828684806824,
    "_timestamp": 1774072203.9861624,
    "eval/mean_token_accuracy": null,
    "train/num_tokens": 2519386.0,
    "eval/num_tokens": null,
    "train/grad_norm": 0.07568359375
  },
  {
    "train/grad_norm": 0.06787109375,
    "train/epoch": 0.33763654419066536,
    "eval/samples_per_second": null,
    "eval/loss": null,
    "train/entropy": 0.7475345358252525,
    "eval/runtime": null,
    "eval/num_tokens": null,
    "_step": 17,
    "eval/steps_per_second": null,
    "_timestamp": 1774072586.026095,
    "eval/entropy": null,
    "train/learning_rate": 1.9798130871033322e-05,
    "train/num_tokens": 2676655.0,
    "train/global_step": 85,
    "_runtime": 6510.017205063,
    "eval/mean_token_accuracy": null,
    "train/loss": 0.7386065006256104,
    "train/mean_token_accuracy": 0.841527795791626
  },
  {
    "train/grad_norm": 0.07080078125,
    "eval/steps_per_second": null,
    "eval/mean_token_accuracy": null,
    "eval/num_tokens": null,
    "_timestamp": 1774072970.7375257,
    "eval/loss": null,
    "train/loss": 0.7357946872711182,
    "train/mean_token_accuracy": 0.8430934965610504,
    "train/learning_rate": 1.975205331789566e-05,
    "_step": 18,
    "train/epoch": 0.35749751737835156,
    "train/entropy": 0.7442873626947403,
    "train/num_tokens": 2834683.0,
    "train/global_step": 90,
    "eval/samples_per_second": null,
    "_runtime": 6894.728690899,
    "eval/entropy": null,
    "eval/runtime": null
  },
  {
    "train/num_tokens": 2991311.0,
    "eval/steps_per_second": null,
    "eval/entropy": null,
    "train/loss": 0.6996148109436036,
    "train/mean_token_accuracy": 0.8516909122467041,
    "train/entropy": 0.70627760887146,
    "train/grad_norm": 0.072265625,
    "eval/mean_token_accuracy": null,
    "train/epoch": 0.37735849056603776,
    "eval/num_tokens": null,
    "eval/samples_per_second": null,
    "_timestamp": 1774073350.0128467,
    "eval/loss": null,
    "train/learning_rate": 1.9701308422911674e-05,
    "_step": 19,
    "_runtime": 7274.003942118,
    "eval/runtime": null,
    "train/global_step": 95
  },
  {
    "train/global_step": 100,
    "train/mean_token_accuracy": 0.8401913166046142,
    "eval/runtime": null,
    "train/num_tokens": 3149669.0,
    "eval/samples_per_second": null,
    "eval/steps_per_second": null,
    "eval/entropy": null,
    "train/loss": 0.7480878829956055,
    "train/learning_rate": 1.964592047263561e-05,
    "train/entropy": 0.751963147521019,
    "_runtime": 7661.162535892,
    "eval/mean_token_accuracy": null,
    "eval/num_tokens": null,
    "_step": 20,
    "train/grad_norm": 0.08154296875,
    "_timestamp": 1774073737.1713939,
    "train/epoch": 0.3972194637537239,
    "eval/loss": null
  },
  {
    "train/grad_norm": 0.06982421875,
    "eval/samples_per_second": null,
    "eval/loss": null,
    "eval/entropy": null,
    "train/loss": 0.7503889083862305,
    "train/mean_token_accuracy": 0.8420647352933883,
    "train/num_tokens": 3307712.0,
    "train/global_step": 105,
    "eval/num_tokens": null,
    "_step": 21,
    "eval/steps_per_second": null,
    "_runtime": 8045.564659893,
    "_timestamp": 1774074121.5735621,
    "eval/mean_token_accuracy": null,
    "eval/runtime": null,
    "train/epoch": 0.4170804369414101,
    "train/learning_rate": 1.958591597579231e-05,
    "train/entropy": 0.750776681303978
  },
  {
    "train/loss": 0.6467480659484863,
    "train/learning_rate": 1.9521323650590135e-05,
    "eval/num_tokens": null,
    "eval/steps_per_second": null,
    "_timestamp": 1774074499.897472,
    "eval/mean_token_accuracy": null,
    "train/epoch": 0.4369414101290963,
    "eval/entropy": null,
    "train/num_tokens": 3463939.0,
    "train/grad_norm": 0.0654296875,
    "_runtime": 8423.888548217,
    "eval/loss": null,
    "train/mean_token_accuracy": 0.8625116974115372,
    "train/global_step": 110,
    "eval/samples_per_second": null,
    "train/entropy": 0.6550520107150077,
    "eval/runtime": null,
    "_step": 22
  },
  {
    "_timestamp": 1774074884.8292186,
    "eval/mean_token_accuracy": null,
    "train/loss": 0.7339670181274414,
    "train/num_tokens": 3621982.0,
    "train/grad_norm": 0.06884765625,
    "eval/entropy": null,
    "train/mean_token_accuracy": 0.8452870637178421,
    "train/learning_rate": 1.9452174410976383e-05,
    "eval/steps_per_second": null,
    "_runtime": 8808.820398993,
    "train/epoch": 0.4568023833167825,
    "eval/runtime": null,
    "train/global_step": 115,
    "_step": 23,
    "eval/loss": null,
    "train/entropy": 0.7343640148639679,
    "eval/num_tokens": null,
    "eval/samples_per_second": null
  },
  {
    "eval/steps_per_second": null,
    "eval/mean_token_accuracy": null,
    "eval/entropy": null,
    "eval/num_tokens": null,
    "train/epoch": 0.4766633565044687,
    "train/loss": 0.6956356048583985,
    "train/learning_rate": 1.9378501351841864e-05,
    "train/entropy": 0.703511294722557,
    "eval/samples_per_second": null,
    "eval/loss": null,
    "train/mean_token_accuracy": 0.8518902719020843,
    "eval/runtime": null,
    "train/num_tokens": 3778985.0,
    "_step": 24,
    "train/grad_norm": 0.076171875,
    "_runtime": 9189.439743356,
    "_timestamp": 1774075265.4485343,
    "train/global_step": 120
  },
  {
    "eval/mean_token_accuracy": null,
    "eval/loss": null,
    "train/loss": 0.6953991889953614,
    "train/mean_token_accuracy": 0.852281242609024,
    "train/num_tokens": 3935682.0,
    "eval/num_tokens": null,
    "eval/steps_per_second": null,
    "_timestamp": 1774075645.3783088,
    "train/entropy": 0.6997133672237397,
    "train/global_step": 125,
    "eval/samples_per_second": null,
    "_step": 25,
    "_runtime": 9569.369402723,
    "eval/runtime": null,
    "train/grad_norm": 0.06787109375,
    "train/epoch": 0.49652432969215493,
    "eval/entropy": null,
    "train/learning_rate": 1.930033973318164e-05
  },
  {
    "_timestamp": 1774076031.2751443,
    "train/epoch": 0.5163853028798411,
    "train/loss": 0.6939593315124511,
    "train/entropy": 0.691907849907875,
    "eval/runtime": null,
    "train/num_tokens": 4093923.0,
    "eval/num_tokens": null,
    "train/grad_norm": 0.064453125,
    "eval/steps_per_second": null,
    "eval/loss": null,
    "_step": 26,
    "_runtime": 9955.266270787,
    "eval/mean_token_accuracy": null,
    "train/mean_token_accuracy": 0.8498972415924072,
    "train/learning_rate": 1.9217726963219567e-05,
    "eval/samples_per_second": null,
    "eval/entropy": null,
    "train/global_step": 130
  },
  {
    "train/entropy": 0.6677081137895584,
    "train/grad_norm": 0.0654296875,
    "_timestamp": 1774076412.524185,
    "eval/loss": null,
    "train/loss": 0.6633842945098877,
    "train/num_tokens": 4251193.0,
    "eval/samples_per_second": null,
    "_step": 27,
    "_runtime": 10336.515392218,
    "train/epoch": 0.5362462760675273,
    "train/learning_rate": 1.9130702580504678e-05,
    "eval/mean_token_accuracy": null,
    "eval/entropy": null,
    "eval/runtime": null,
    "train/global_step": 135,
    "eval/num_tokens": null,
    "eval/steps_per_second": null,
    "train/mean_token_accuracy": 0.8582272171974182
  },
  {
    "eval/steps_per_second": null,
    "_runtime": 10720.178591916,
    "_timestamp": 1774076796.1874793,
    "eval/loss": null,
    "train/learning_rate": 1.903930823498799e-05,
    "eval/samples_per_second": null,
    "train/grad_norm": 0.0732421875,
    "eval/entropy": null,
    "train/loss": 0.7289260387420654,
    "train/global_step": 140,
    "eval/num_tokens": null,
    "eval/runtime": null,
    "train/num_tokens": 4408792.0,
    "eval/mean_token_accuracy": null,
    "train/epoch": 0.5561072492552135,
    "train/mean_token_accuracy": 0.8412359774112701,
    "train/entropy": 0.7320046246051788,
    "_step": 28
  },
  {
    "eval/steps_per_second": null,
    "eval/entropy": null,
    "train/entropy": 0.6800097614526749,
    "eval/runtime": null,
    "train/num_tokens": 4565907.0,
    "train/global_step": 145,
    "_runtime": 11100.789637176,
    "_timestamp": 1774077176.7984781,
    "eval/loss": null,
    "train/learning_rate": 1.894358766808883e-05,
    "eval/samples_per_second": null,
    "_step": 29,
    "eval/mean_token_accuracy": null,
    "train/loss": 0.6826032638549805,
    "train/mean_token_accuracy": 0.8534978479146957,
    "train/grad_norm": 0.08642578125,
    "train/epoch": 0.5759682224428997,
    "eval/num_tokens": null
  },
  {
    "train/grad_norm": 0.07080078125,
    "eval/loss": null,
    "train/loss": 0.6757159233093262,
    "train/learning_rate": 1.884358669176011e-05,
    "eval/runtime": null,
    "eval/samples_per_second": null,
    "_step": 30,
    "_timestamp": 1774077560.0471594,
    "eval/entropy": null,
    "train/mean_token_accuracy": 0.8548094302415847,
    "eval/mean_token_accuracy": null,
    "train/entropy": 0.6818895429372788,
    "train/global_step": 150,
    "eval/num_tokens": null,
    "eval/steps_per_second": null,
    "_runtime": 11484.038213721,
    "train/epoch": 0.5958291956305859,
    "train/num_tokens": 4723379.0
  },
  {
    "eval/loss": null,
    "eval/samples_per_second": null,
    "_runtime": 11869.971236708,
    "eval/mean_token_accuracy": null,
    "train/loss": 0.6638399600982666,
    "_step": 31,
    "train/grad_norm": 0.07470703125,
    "eval/steps_per_second": null,
    "_timestamp": 1774077945.9800444,
    "train/epoch": 0.6156901688182721,
    "eval/entropy": null,
    "eval/runtime": null,
    "train/mean_token_accuracy": 0.8590966641902924,
    "train/learning_rate": 1.87393531665627e-05,
    "train/entropy": 0.6685345828533172,
    "train/num_tokens": 4881340.0,
    "train/global_step": 155,
    "eval/num_tokens": null
  },
  {
    "eval/entropy": null,
    "train/mean_token_accuracy": 0.8515608012676239,
    "train/learning_rate": 1.8630936978759337e-05,
    "eval/samples_per_second": null,
    "eval/mean_token_accuracy": null,
    "train/entropy": 0.6932751849293709,
    "train/num_tokens": 5039277.0,
    "train/global_step": 160,
    "_step": 32,
    "eval/steps_per_second": null,
    "_runtime": 12254.501590913,
    "_timestamp": 1774078330.5103698,
    "eval/runtime": null,
    "train/grad_norm": 0.0654296875,
    "train/epoch": 0.6355511420059583,
    "eval/loss": null,
    "train/loss": 0.6913290977478027,
    "eval/num_tokens": null
  },
  {
    "eval/samples_per_second": null,
    "_step": 33,
    "eval/steps_per_second": null,
    "train/epoch": 0.6554121151936445,
    "train/entropy": 0.6878215938806533,
    "train/num_tokens": 5197288.0,
    "_runtime": 12639.388033415,
    "eval/loss": null,
    "train/loss": 0.6833026885986329,
    "train/grad_norm": 0.06787109375,
    "eval/mean_token_accuracy": null,
    "train/mean_token_accuracy": 0.852669021487236,
    "train/learning_rate": 1.851839001643898e-05,
    "_timestamp": 1774078715.3968143,
    "eval/entropy": null,
    "eval/runtime": null,
    "train/global_step": 165,
    "eval/num_tokens": null
  },
  {
    "_step": 34,
    "train/grad_norm": 0.0673828125,
    "eval/steps_per_second": null,
    "eval/entropy": null,
    "train/entropy": 0.6983172535896301,
    "_runtime": 13022.121386954,
    "eval/mean_token_accuracy": null,
    "train/loss": 0.6999450206756592,
    "train/learning_rate": 1.8401766144683145e-05,
    "eval/samples_per_second": null,
    "train/num_tokens": 5354782.0,
    "eval/num_tokens": null,
    "eval/runtime": null,
    "_timestamp": 1774079098.1302335,
    "train/epoch": 0.6752730883813307,
    "eval/loss": null,
    "train/mean_token_accuracy": 0.8498626083135605,
    "train/global_step": 170
  },
  {
    "train/global_step": 175,
    "eval/num_tokens": null,
    "_step": 35,
    "train/grad_norm": 0.0673828125,
    "eval/loss": null,
    "eval/entropy": null,
    "train/entropy": 0.6679067879915237,
    "train/mean_token_accuracy": 0.8557754755020142,
    "eval/runtime": null,
    "train/num_tokens": 5512760.0,
    "eval/samples_per_second": null,
    "_runtime": 13406.511818782,
    "eval/mean_token_accuracy": null,
    "train/epoch": 0.6951340615690169,
    "train/loss": 0.669780158996582,
    "eval/steps_per_second": null,
    "_timestamp": 1774079482.5207052,
    "train/learning_rate": 1.8281121179786024e-05
  },
  {
    "train/epoch": 0.7149950347567031,
    "eval/loss": null,
    "eval/entropy": null,
    "train/num_tokens": 5670231.0,
    "eval/steps_per_second": null,
    "train/loss": 0.6662922382354737,
    "train/entropy": 0.6665785640478135,
    "eval/num_tokens": null,
    "_step": 36,
    "_runtime": 13789.328493652,
    "eval/mean_token_accuracy": null,
    "train/global_step": 180,
    "train/grad_norm": 0.0654296875,
    "train/mean_token_accuracy": 0.8539770424365998,
    "train/learning_rate": 1.815651286254074e-05,
    "eval/runtime": null,
    "eval/samples_per_second": null,
    "_timestamp": 1774079865.3373394
  },
  {
    "_timestamp": 1774080250.9091277,
    "eval/runtime": null,
    "eval/num_tokens": null,
    "train/learning_rate": 1.802800083060457e-05,
    "train/entropy": 0.6473378300666809,
    "train/num_tokens": 5828152.0,
    "eval/samples_per_second": null,
    "_step": 37,
    "train/epoch": 0.7348560079443893,
    "eval/loss": null,
    "train/loss": 0.6500232219696045,
    "train/grad_norm": 0.06396484375,
    "eval/steps_per_second": null,
    "_runtime": 14174.900261181,
    "eval/mean_token_accuracy": null,
    "eval/entropy": null,
    "train/mean_token_accuracy": 0.8588274091482162,
    "train/global_step": 185
  },
  {
    "eval/entropy": null,
    "train/learning_rate": 1.7895646589956294e-05,
    "eval/runtime": null,
    "train/global_step": 190,
    "train/grad_norm": 0.06494140625,
    "eval/steps_per_second": null,
    "_runtime": 14557.392865611,
    "eval/mean_token_accuracy": null,
    "train/epoch": 0.7547169811320755,
    "train/loss": 0.63482666015625,
    "train/mean_token_accuracy": 0.8619981378316879,
    "train/entropy": 0.642140018939972,
    "train/num_tokens": 5985518.0,
    "eval/num_tokens": null,
    "_step": 38,
    "_timestamp": 1774080633.4016142,
    "eval/loss": null,
    "eval/samples_per_second": null
  },
  {
    "eval/samples_per_second": null,
    "eval/steps_per_second": null,
    "_step": 39,
    "eval/runtime": null,
    "train/num_tokens": 6144069.0,
    "train/epoch": 0.7745779543197616,
    "eval/entropy": null,
    "train/entropy": 0.6907416492700577,
    "train/global_step": 195,
    "eval/num_tokens": null,
    "eval/loss": null,
    "train/loss": 0.6893678188323975,
    "train/learning_rate": 1.7759513485459367e-05,
    "train/grad_norm": 0.07470703125,
    "_runtime": 14944.521440678,
    "_timestamp": 1774081020.5303519,
    "eval/mean_token_accuracy": null,
    "train/mean_token_accuracy": 0.8496612876653671
  },
  {
    "train/grad_norm": 0.0771484375,
    "_runtime": 15331.823331372,
    "train/loss": 0.6649993896484375,
    "eval/num_tokens": null,
    "eval/samples_per_second": null,
    "eval/mean_token_accuracy": null,
    "train/epoch": 0.7944389275074478,
    "eval/loss": null,
    "train/mean_token_accuracy": 0.8541058480739594,
    "eval/runtime": null,
    "_timestamp": 1774081407.8321784,
    "train/learning_rate": 1.7619666670545034e-05,
    "train/global_step": 200,
    "_step": 40,
    "eval/steps_per_second": null,
    "eval/entropy": null,
    "train/entropy": 0.6658471643924713,
    "train/num_tokens": 6302572.0
  },
  {
    "train/num_tokens": null,
    "_runtime": 15617.466923457,
    "_timestamp": 1774081693.4758987,
    "train/loss": null,
    "train/mean_token_accuracy": null,
    "train/grad_norm": null,
    "eval/loss": 0.6385018229484558,
    "eval/runtime": 285.6419,
    "eval/samples_per_second": 3.084,
    "eval/steps_per_second": 0.389,
    "train/epoch": 0.7944389275074478,
    "eval/entropy": 0.6371658033615833,
    "train/learning_rate": null,
    "eval/num_tokens": 6302572.0,
    "eval/mean_token_accuracy": 0.8616338941428039,
    "train/entropy": null,
    "train/global_step": 200,
    "_step": 41
  },
  {
    "eval/loss": null,
    "eval/entropy": null,
    "eval/runtime": null,
    "train/num_tokens": 6460030.0,
    "eval/samples_per_second": null,
    "_runtime": 16004.535008899,
    "train/entropy": 0.6162068992853165,
    "_step": 42,
    "train/grad_norm": 0.0830078125,
    "eval/steps_per_second": null,
    "eval/mean_token_accuracy": null,
    "train/loss": 0.6140308856964112,
    "train/learning_rate": 1.747617307602982e-05,
    "train/global_step": 205,
    "_timestamp": 1774082080.5437562,
    "train/mean_token_accuracy": 0.8641094267368317,
    "eval/num_tokens": null,
    "train/epoch": 0.814299900695134
  },
  {
    "train/epoch": 0.8341608738828202,
    "train/entropy": 0.6609851658344269,
    "eval/runtime": null,
    "train/num_tokens": 6616145.0,
    "eval/num_tokens": null,
    "eval/samples_per_second": null,
    "_timestamp": 1774082459.3766973,
    "train/loss": 0.6652685165405273,
    "train/global_step": 210,
    "train/grad_norm": 0.07177734375,
    "eval/steps_per_second": null,
    "eval/mean_token_accuracy": null,
    "eval/loss": null,
    "eval/entropy": null,
    "train/learning_rate": 1.7329101378082374e-05,
    "train/mean_token_accuracy": 0.8539849042892456,
    "_step": 43,
    "_runtime": 16383.367974387
  },
  {
    "train/grad_norm": 0.0830078125,
    "eval/steps_per_second": null,
    "eval/samples_per_second": null,
    "_runtime": 16769.064276408,
    "eval/entropy": null,
    "train/learning_rate": 1.7178521965354992e-05,
    "eval/num_tokens": null,
    "train/num_tokens": 6774200.0,
    "_timestamp": 1774082845.073149,
    "eval/mean_token_accuracy": null,
    "train/epoch": 0.8540218470705064,
    "eval/loss": null,
    "train/loss": 0.619290828704834,
    "train/mean_token_accuracy": 0.8651538789272308,
    "train/entropy": 0.6210699826478958,
    "eval/runtime": null,
    "train/global_step": 215,
    "_step": 44
  },
  {
    "eval/loss": null,
    "eval/entropy": null,
    "eval/samples_per_second": null,
    "_step": 45,
    "eval/mean_token_accuracy": null,
    "train/epoch": 0.8738828202581926,
    "train/mean_token_accuracy": 0.8633539229631424,
    "train/entropy": 0.6352832973003387,
    "train/num_tokens": 6931962.0,
    "train/global_step": 220,
    "eval/num_tokens": null,
    "eval/steps_per_second": null,
    "train/loss": 0.6326572895050049,
    "eval/runtime": null,
    "train/learning_rate": 1.7024506905295566e-05,
    "train/grad_norm": 0.06689453125,
    "_runtime": 17153.674871091,
    "_timestamp": 1774083229.683625
  },
  {
    "eval/loss": null,
    "eval/entropy": null,
    "_step": 46,
    "_runtime": 17539.298860844,
    "train/epoch": 0.8937437934458788,
    "train/num_tokens": 7090074.0,
    "train/global_step": 225,
    "eval/samples_per_second": null,
    "train/grad_norm": 0.072265625,
    "train/entropy": 0.7038206264376641,
    "eval/steps_per_second": null,
    "_timestamp": 1774083615.3078098,
    "train/loss": 0.7063935279846192,
    "train/mean_token_accuracy": 0.8464726775884628,
    "train/learning_rate": 1.6867129909656e-05,
    "eval/runtime": null,
    "eval/num_tokens": null,
    "eval/mean_token_accuracy": null
  },
  {
    "train/epoch": 0.913604766633565,
    "eval/loss": null,
    "eval/entropy": null,
    "_runtime": 17928.496533396,
    "_timestamp": 1774084004.5052743,
    "eval/mean_token_accuracy": null,
    "train/mean_token_accuracy": 0.8513082385063171,
    "train/global_step": 230,
    "eval/num_tokens": null,
    "eval/samples_per_second": null,
    "train/loss": 0.6751947402954102,
    "train/learning_rate": 1.6706466299213718e-05,
    "train/entropy": 0.6752635329961777,
    "_step": 47,
    "train/grad_norm": 0.0673828125,
    "eval/steps_per_second": null,
    "eval/runtime": null,
    "train/num_tokens": 7249064.0
  },
  {
    "train/loss": 0.6660223484039307,
    "train/learning_rate": 1.6542592967723065e-05,
    "eval/runtime": null,
    "train/num_tokens": 7407242.0,
    "eval/num_tokens": null,
    "_runtime": 18314.644903027,
    "eval/loss": null,
    "train/global_step": 235,
    "_step": 48,
    "_timestamp": 1774084390.6536868,
    "train/epoch": 0.9334657398212513,
    "train/grad_norm": 0.0859375,
    "eval/steps_per_second": null,
    "eval/mean_token_accuracy": null,
    "eval/entropy": null,
    "train/mean_token_accuracy": 0.8559522092342376,
    "train/entropy": 0.6636946976184845,
    "eval/samples_per_second": null
  },
  {
    "eval/runtime": null,
    "train/num_tokens": 7564470.0,
    "_runtime": 18696.774008429,
    "eval/mean_token_accuracy": null,
    "eval/entropy": null,
    "train/loss": 0.699138879776001,
    "train/mean_token_accuracy": 0.8477810889482498,
    "eval/loss": null,
    "train/learning_rate": 1.6375588345113895e-05,
    "train/entropy": 0.7004503205418586,
    "eval/steps_per_second": null,
    "_timestamp": 1774084772.7829225,
    "train/epoch": 0.9533267130089375,
    "train/global_step": 240,
    "eval/num_tokens": null,
    "train/grad_norm": 0.08642578125,
    "eval/samples_per_second": null,
    "_step": 49
  },
  {
    "train/mean_token_accuracy": 0.866635861992836,
    "_step": 50,
    "train/epoch": 0.9731876861966237,
    "eval/samples_per_second": null,
    "_runtime": 19084.737536336,
    "eval/mean_token_accuracy": null,
    "eval/loss": null,
    "train/learning_rate": 1.6205532359954905e-05,
    "eval/num_tokens": null,
    "_timestamp": 1774085160.7463315,
    "train/loss": 0.6119746208190918,
    "eval/runtime": null,
    "train/num_tokens": 7722940.0,
    "train/global_step": 245,
    "train/entropy": 0.6121954590082168,
    "train/grad_norm": 0.07373046875,
    "eval/steps_per_second": null,
    "eval/entropy": null
  },
  {
    "train/grad_norm": 0.072265625,
    "train/mean_token_accuracy": 0.8614127308130264,
    "train/learning_rate": 1.603250640119977e-05,
    "eval/steps_per_second": null,
    "_timestamp": 1774085542.63536,
    "eval/mean_token_accuracy": null,
    "eval/loss": null,
    "train/loss": 0.6367170810699463,
    "train/entropy": 0.63861543238163,
    "eval/runtime": null,
    "train/num_tokens": 7880190.0,
    "eval/entropy": null,
    "train/global_step": 250,
    "eval/num_tokens": null,
    "eval/samples_per_second": null,
    "_runtime": 19466.626442937,
    "train/epoch": 0.9930486593843099,
    "_step": 51
  },
  {
    "eval/loss": null,
    "train/mean_token_accuracy": 0.8682849564050373,
    "_step": 52,
    "train/entropy": 0.6015533648039165,
    "eval/runtime": null,
    "eval/steps_per_second": null,
    "_runtime": 19802.895186477,
    "eval/entropy": null,
    "eval/samples_per_second": null,
    "_timestamp": 1774085878.9039435,
    "train/num_tokens": 8020105.0,
    "eval/num_tokens": null,
    "train/grad_norm": 0.0712890625,
    "eval/mean_token_accuracy": null,
    "train/epoch": 1.0119165839126116,
    "train/loss": 0.5996394157409668,
    "train/learning_rate": 1.585659327923432e-05,
    "train/global_step": 255
  },
  {
    "train/epoch": 1.0317775571002978,
    "eval/entropy": null,
    "train/mean_token_accuracy": 0.8573653608560562,
    "train/entropy": 0.6507866397500038,
    "eval/num_tokens": null,
    "_step": 53,
    "eval/steps_per_second": null,
    "_timestamp": 1774086263.7754405,
    "eval/mean_token_accuracy": null,
    "train/num_tokens": 8177793.0,
    "eval/samples_per_second": null,
    "train/grad_norm": 0.07275390625,
    "eval/loss": null,
    "train/learning_rate": 1.567787718624338e-05,
    "train/global_step": 260,
    "train/loss": 0.6561660289764404,
    "eval/runtime": null,
    "_runtime": 20187.766608423
  },
  {
    "train/grad_norm": 0.07080078125,
    "train/loss": 0.7012579917907715,
    "train/learning_rate": 1.5496443655916348e-05,
    "train/global_step": 265,
    "eval/num_tokens": null,
    "_step": 54,
    "eval/entropy": null,
    "train/mean_token_accuracy": 0.8462246209383011,
    "eval/steps_per_second": null,
    "_runtime": 20572.976858003,
    "_timestamp": 1774086648.9857852,
    "train/epoch": 1.051638530287984,
    "eval/loss": null,
    "train/entropy": 0.6965876191854476,
    "eval/runtime": null,
    "eval/samples_per_second": null,
    "eval/mean_token_accuracy": null,
    "train/num_tokens": 8335782.0
  },
  {
    "eval/runtime": null,
    "eval/num_tokens": null,
    "train/grad_norm": 0.07275390625,
    "train/global_step": 270,
    "train/epoch": 1.0714995034756702,
    "eval/loss": null,
    "train/loss": 0.6189123153686523,
    "train/mean_token_accuracy": 0.8641173124313355,
    "train/learning_rate": 1.5312379522510666e-05,
    "train/entropy": 0.6225355282425881,
    "_step": 55,
    "eval/steps_per_second": null,
    "_runtime": 20957.087267504,
    "train/num_tokens": 8493789.0,
    "eval/samples_per_second": null,
    "_timestamp": 1774087033.096043,
    "eval/mean_token_accuracy": null,
    "eval/entropy": null
  },
  {
    "train/grad_norm": 0.07470703125,
    "eval/steps_per_second": null,
    "eval/mean_token_accuracy": null,
    "train/learning_rate": 1.512577287929288e-05,
    "_runtime": 21344.254417866,
    "_timestamp": 1774087420.2632637,
    "eval/loss": null,
    "eval/runtime": null,
    "eval/num_tokens": null,
    "eval/samples_per_second": null,
    "eval/entropy": null,
    "train/mean_token_accuracy": 0.8527255982160569,
    "train/num_tokens": 8652426.0,
    "train/global_step": 275,
    "train/epoch": 1.0913604766633564,
    "train/loss": 0.6758854866027832,
    "train/entropy": 0.6701275780797005,
    "_step": 56
  },
  {
    "_timestamp": 1774087800.1862075,
    "train/learning_rate": 1.4936713036377102e-05,
    "train/entropy": 0.6163221091032028,
    "train/num_tokens": 8808920.0,
    "eval/num_tokens": null,
    "eval/samples_per_second": null,
    "_runtime": 21724.177458602,
    "eval/mean_token_accuracy": null,
    "train/epoch": 1.1112214498510427,
    "train/mean_token_accuracy": 0.863449314236641,
    "_step": 57,
    "eval/steps_per_second": null,
    "eval/runtime": null,
    "train/global_step": 280,
    "train/grad_norm": 0.06787109375,
    "eval/loss": null,
    "eval/entropy": null,
    "train/loss": 0.6162703037261963
  },
  {
    "train/grad_norm": 0.0751953125,
    "eval/entropy": null,
    "train/global_step": 285,
    "eval/steps_per_second": null,
    "eval/loss": null,
    "train/entropy": 0.6692247822880745,
    "eval/runtime": null,
    "eval/num_tokens": null,
    "_step": 58,
    "_timestamp": 1774088178.7900872,
    "eval/mean_token_accuracy": null,
    "train/loss": 0.669809103012085,
    "train/mean_token_accuracy": 0.85242800116539,
    "train/num_tokens": 8965076.0,
    "_runtime": 22102.781274906,
    "train/epoch": 1.1310824230387289,
    "train/learning_rate": 1.474529047798112e-05,
    "eval/samples_per_second": null
  },
  {
    "eval/steps_per_second": null,
    "train/num_tokens": 9121956.0,
    "train/global_step": 290,
    "_runtime": 22484.536656617,
    "train/loss": 0.6573848247528076,
    "eval/num_tokens": null,
    "eval/samples_per_second": null,
    "_step": 59,
    "_timestamp": 1774088560.545437,
    "train/epoch": 1.150943396226415,
    "eval/entropy": null,
    "train/mean_token_accuracy": 0.857552570104599,
    "eval/runtime": null,
    "train/grad_norm": 0.0673828125,
    "eval/mean_token_accuracy": null,
    "eval/loss": null,
    "train/learning_rate": 1.4551596819120564e-05,
    "train/entropy": 0.6671645537018775
  },
  {
    "train/grad_norm": 0.078125,
    "eval/mean_token_accuracy": null,
    "train/epoch": 1.1708043694141013,
    "train/mean_token_accuracy": 0.8409671127796173,
    "train/entropy": 0.7160604387521744,
    "_timestamp": 1774088944.914286,
    "train/loss": 0.7200253486633301,
    "train/global_step": 295,
    "eval/samples_per_second": null,
    "eval/runtime": null,
    "_runtime": 22868.90537286,
    "eval/loss": null,
    "eval/entropy": null,
    "eval/num_tokens": null,
    "eval/steps_per_second": null,
    "train/learning_rate": 1.435572476176187e-05,
    "train/num_tokens": 9279866.0,
    "_step": 60
  },
  {
    "train/loss": 0.6095530986785889,
    "_step": 61,
    "eval/entropy": null,
    "train/learning_rate": 1.4157768050455038e-05,
    "train/entropy": 0.6146274298429489,
    "eval/runtime": null,
    "eval/num_tokens": null,
    "_runtime": 23253.445604194,
    "_timestamp": 1774089329.4543924,
    "eval/mean_token_accuracy": null,
    "train/mean_token_accuracy": 0.8664685249328613,
    "eval/samples_per_second": null,
    "eval/steps_per_second": null,
    "train/num_tokens": 9437665.0,
    "train/global_step": 300,
    "train/grad_norm": 0.06884765625,
    "train/epoch": 1.1906653426017875,
    "eval/loss": null
  },
  {
    "eval/samples_per_second": null,
    "train/grad_norm": 0.0712890625,
    "_runtime": 23639.174083016,
    "eval/loss": null,
    "eval/runtime": null,
    "train/global_step": 305,
    "_step": 62,
    "train/epoch": 1.2105263157894737,
    "train/mean_token_accuracy": 0.8620329767465591,
    "eval/mean_token_accuracy": null,
    "train/learning_rate": 1.3957821427467392e-05,
    "eval/steps_per_second": null,
    "_timestamp": 1774089715.1829264,
    "eval/entropy": null,
    "train/loss": 0.6287214279174804,
    "train/entropy": 0.6286943182349205,
    "train/num_tokens": 9595880.0,
    "eval/num_tokens": null
  },
  {
    "_runtime": 24021.990000343,
    "_timestamp": 1774090097.9987402,
    "train/epoch": 1.2303872889771599,
    "train/loss": 0.6421625137329101,
    "train/grad_norm": 0.07080078125,
    "eval/steps_per_second": null,
    "eval/runtime": null,
    "eval/num_tokens": null,
    "_step": 63,
    "eval/mean_token_accuracy": null,
    "train/learning_rate": 1.3755980587439857e-05,
    "train/entropy": 0.6465730503201484,
    "train/num_tokens": 9753404.0,
    "eval/loss": null,
    "eval/entropy": null,
    "train/mean_token_accuracy": 0.8585933595895767,
    "train/global_step": 310,
    "eval/samples_per_second": null
  },
  {
    "eval/steps_per_second": null,
    "train/learning_rate": 1.3552342131587399e-05,
    "train/entropy": 0.6549025014042854,
    "eval/samples_per_second": null,
    "_timestamp": 1774090481.1636603,
    "train/epoch": 1.250248262164846,
    "eval/loss": null,
    "eval/entropy": null,
    "train/grad_norm": 0.06640625,
    "eval/mean_token_accuracy": null,
    "train/loss": 0.6479173183441163,
    "train/mean_token_accuracy": 0.8572903662919998,
    "train/num_tokens": 9911098.0,
    "train/global_step": 315,
    "_runtime": 24405.154857855,
    "eval/runtime": null,
    "eval/num_tokens": null,
    "_step": 64
  },
  {
    "eval/samples_per_second": null,
    "eval/steps_per_second": null,
    "train/learning_rate": 1.334700352146561e-05,
    "train/entropy": 0.5844791054725647,
    "eval/runtime": null,
    "train/num_tokens": 10067398.0,
    "_runtime": 24783.863753097,
    "eval/entropy": null,
    "train/loss": 0.5892719745635986,
    "train/mean_token_accuracy": 0.8718775898218155,
    "train/global_step": 320,
    "_step": 65,
    "train/grad_norm": 0.076171875,
    "_timestamp": 1774090859.872544,
    "eval/mean_token_accuracy": null,
    "train/epoch": 1.2701092353525323,
    "eval/loss": null,
    "eval/num_tokens": null
  },
  {
    "train/num_tokens": 10226507.0,
    "train/global_step": 325,
    "_step": 66,
    "train/grad_norm": 0.07470703125,
    "_runtime": 25174.719320985,
    "train/mean_token_accuracy": 0.8653858661651611,
    "train/learning_rate": 1.3140063032325491e-05,
    "train/entropy": 0.6069152429699898,
    "eval/loss": null,
    "eval/entropy": null,
    "train/loss": 0.6055289745330811,
    "eval/samples_per_second": null,
    "eval/steps_per_second": null,
    "eval/mean_token_accuracy": null,
    "eval/num_tokens": null,
    "_timestamp": 1774091250.7281735,
    "train/epoch": 1.2899702085402185,
    "eval/runtime": null
  },
  {
    "eval/runtime": null,
    "train/global_step": 330,
    "eval/samples_per_second": null,
    "_timestamp": 1774091636.409249,
    "eval/mean_token_accuracy": null,
    "eval/entropy": null,
    "train/learning_rate": 1.2931619706078862e-05,
    "train/num_tokens": 10384719.0,
    "eval/num_tokens": null,
    "eval/steps_per_second": null,
    "train/epoch": 1.3098311817279047,
    "train/loss": 0.6673394203186035,
    "train/grad_norm": 0.07373046875,
    "_step": 67,
    "_runtime": 25560.400428104,
    "eval/loss": null,
    "train/mean_token_accuracy": 0.8535583227872848,
    "train/entropy": 0.6702021941542625
  },
  {
    "_timestamp": 1774092021.9554133,
    "train/epoch": 1.329692154915591,
    "eval/entropy": null,
    "train/mean_token_accuracy": 0.8600308716297149,
    "train/entropy": 0.6417001917958259,
    "eval/runtime": null,
    "train/grad_norm": 0.06640625,
    "eval/steps_per_second": null,
    "_runtime": 25945.946639662,
    "eval/mean_token_accuracy": null,
    "train/num_tokens": 10543013.0,
    "train/global_step": 335,
    "_step": 68,
    "train/loss": 0.638443899154663,
    "train/learning_rate": 1.2721773303896765e-05,
    "eval/num_tokens": null,
    "eval/samples_per_second": null,
    "eval/loss": null
  },
  {
    "eval/samples_per_second": null,
    "_timestamp": 1774092403.7089396,
    "eval/mean_token_accuracy": null,
    "train/learning_rate": 1.2510624258463719e-05,
    "train/entropy": 0.5709571048617363,
    "train/num_tokens": 10700202.0,
    "eval/num_tokens": null,
    "train/grad_norm": 0.06591796875,
    "eval/entropy": null,
    "train/mean_token_accuracy": 0.8736646473407745,
    "eval/runtime": null,
    "train/epoch": 1.349553128103277,
    "train/global_step": 340,
    "_step": 69,
    "eval/steps_per_second": null,
    "_runtime": 26327.700163481,
    "eval/loss": null,
    "train/loss": 0.5714692592620849
  },
  {
    "eval/runtime": null,
    "eval/steps_per_second": null,
    "eval/loss": null,
    "train/learning_rate": 1.2298273625910512e-05,
    "train/num_tokens": 10858283.0,
    "train/global_step": 345,
    "_runtime": 26712.93759689,
    "eval/num_tokens": null,
    "_step": 70,
    "_timestamp": 1774092788.946405,
    "eval/mean_token_accuracy": null,
    "train/epoch": 1.3694141012909633,
    "eval/entropy": null,
    "train/entropy": 0.6414237916469574,
    "eval/samples_per_second": null,
    "train/grad_norm": 0.07421875,
    "train/loss": 0.6403416156768799,
    "train/mean_token_accuracy": 0.85959213078022
  },
  {
    "_timestamp": 1774093174.2614155,
    "train/epoch": 1.3892750744786495,
    "eval/entropy": null,
    "train/grad_norm": 0.07177734375,
    "eval/steps_per_second": null,
    "_runtime": 27098.252612233,
    "eval/mean_token_accuracy": null,
    "eval/loss": null,
    "train/mean_token_accuracy": 0.8710377424955368,
    "train/learning_rate": 1.2084823037448654e-05,
    "train/global_step": 350,
    "eval/num_tokens": null,
    "eval/samples_per_second": null,
    "_step": 71,
    "train/entropy": 0.585646390914917,
    "eval/runtime": null,
    "train/num_tokens": 11016305.0,
    "train/loss": 0.5818086624145508
  },
  {
    "train/learning_rate": 1.1870374650729582e-05,
    "train/entropy": 0.6353900447487831,
    "eval/num_tokens": null,
    "eval/steps_per_second": null,
    "_runtime": 27481.899182785,
    "_timestamp": 1774093557.9079568,
    "train/loss": 0.634014892578125,
    "eval/runtime": null,
    "train/global_step": 355,
    "train/epoch": 1.4091360476663357,
    "eval/loss": null,
    "eval/samples_per_second": null,
    "_step": 72,
    "train/grad_norm": 0.07275390625,
    "eval/entropy": null,
    "train/num_tokens": 11173697.0,
    "eval/mean_token_accuracy": null,
    "train/mean_token_accuracy": 0.860898807644844
  },
  {
    "eval/steps_per_second": null,
    "_timestamp": 1774093941.4145908,
    "eval/loss": null,
    "eval/entropy": null,
    "eval/num_tokens": null,
    "eval/samples_per_second": null,
    "train/entropy": 0.6848996058106422,
    "_step": 73,
    "train/grad_norm": 0.0810546875,
    "_runtime": 27865.405773437,
    "eval/mean_token_accuracy": null,
    "train/loss": 0.6894534587860107,
    "train/global_step": 360,
    "train/epoch": 1.428997020854022,
    "train/mean_token_accuracy": 0.848519578576088,
    "train/learning_rate": 1.165503110095191e-05,
    "eval/runtime": null,
    "train/num_tokens": 11331272.0
  },
  {
    "train/grad_norm": 0.07373046875,
    "train/epoch": 1.4488579940417081,
    "train/learning_rate": 1.1438895451740141e-05,
    "eval/samples_per_second": null,
    "_timestamp": 1774094318.8456092,
    "eval/loss": null,
    "eval/entropy": null,
    "train/num_tokens": 11487337.0,
    "_step": 74,
    "eval/mean_token_accuracy": null,
    "train/loss": 0.5958111763000489,
    "train/mean_token_accuracy": 0.8681195348501205,
    "eval/steps_per_second": null,
    "_runtime": 28242.836711664,
    "train/entropy": 0.5993810370564461,
    "eval/runtime": null,
    "train/global_step": 365,
    "eval/num_tokens": null
  },
  {
    "train/grad_norm": 0.07080078125,
    "_runtime": 28624.87282145,
    "train/learning_rate": 1.1222071145818293e-05,
    "train/num_tokens": 11644486.0,
    "train/global_step": 370,
    "eval/samples_per_second": null,
    "eval/loss": null,
    "eval/entropy": null,
    "train/mean_token_accuracy": 0.8550859063863754,
    "eval/runtime": null,
    "train/epoch": 1.4687189672293943,
    "train/loss": 0.6495057106018066,
    "train/entropy": 0.6574522584676743,
    "eval/num_tokens": null,
    "eval/steps_per_second": null,
    "_timestamp": 1774094700.88158,
    "eval/mean_token_accuracy": null,
    "_step": 75
  },
  {
    "eval/steps_per_second": null,
    "train/epoch": 1.4885799404170803,
    "eval/loss": null,
    "train/entropy": 0.622519738972187,
    "_step": 76,
    "_timestamp": 1774095080.037608,
    "eval/entropy": null,
    "train/mean_token_accuracy": 0.8629825413227081,
    "eval/mean_token_accuracy": null,
    "train/loss": 0.6314330101013184,
    "train/learning_rate": 1.1004661955502143e-05,
    "train/num_tokens": 11800984.0,
    "eval/num_tokens": null,
    "eval/samples_per_second": null,
    "train/grad_norm": 0.072265625,
    "_runtime": 29004.028961457,
    "eval/runtime": null,
    "train/global_step": 375
  },
  {
    "eval/mean_token_accuracy": null,
    "train/epoch": 1.5084409136047667,
    "eval/entropy": null,
    "train/entropy": 0.6319662347435951,
    "_timestamp": 1774095465.5642598,
    "train/loss": 0.6253130435943604,
    "train/learning_rate": 1.0786771933033677e-05,
    "eval/runtime": null,
    "train/global_step": 380,
    "eval/num_tokens": null,
    "_step": 77,
    "train/grad_norm": 0.07373046875,
    "eval/steps_per_second": null,
    "eval/samples_per_second": null,
    "_runtime": 29389.555515061,
    "eval/loss": null,
    "train/mean_token_accuracy": 0.8611183851957321,
    "train/num_tokens": 11959253.0
  },
  {
    "train/entropy": 0.6124561101198196,
    "_timestamp": 1774095850.4805372,
    "eval/mean_token_accuracy": null,
    "train/epoch": 1.5283018867924527,
    "eval/loss": null,
    "train/loss": 0.6073987483978271,
    "eval/num_tokens": null,
    "eval/entropy": null,
    "eval/runtime": null,
    "train/num_tokens": 12117263.0,
    "train/grad_norm": 0.0830078125,
    "eval/steps_per_second": null,
    "_runtime": 29774.471646873,
    "train/mean_token_accuracy": 0.8645203709602356,
    "train/learning_rate": 1.0568505360781606e-05,
    "train/global_step": 385,
    "eval/samples_per_second": null,
    "_step": 78
  },
  {
    "train/mean_token_accuracy": 0.848421972990036,
    "eval/num_tokens": null,
    "_timestamp": 1774096234.9510064,
    "train/epoch": 1.5481628599801391,
    "train/num_tokens": 12275207.0,
    "train/global_step": 390,
    "train/learning_rate": 1.0349966701331721e-05,
    "train/entropy": 0.696194814145565,
    "eval/runtime": null,
    "eval/entropy": null,
    "train/loss": 0.6984506130218506,
    "eval/samples_per_second": null,
    "_step": 79,
    "train/grad_norm": 0.07421875,
    "eval/steps_per_second": null,
    "_runtime": 30158.942218477,
    "eval/mean_token_accuracy": null,
    "eval/loss": null
  },
  {
    "_step": 80,
    "train/grad_norm": 0.07177734375,
    "_runtime": 30539.964873738,
    "_timestamp": 1774096615.9736338,
    "train/mean_token_accuracy": 0.860705554485321,
    "eval/num_tokens": null,
    "train/global_step": 395,
    "eval/runtime": null,
    "eval/mean_token_accuracy": null,
    "eval/entropy": null,
    "train/learning_rate": 1.013126054749099e-05,
    "train/entropy": 0.637154632806778,
    "eval/steps_per_second": null,
    "train/epoch": 1.5680238331678251,
    "eval/loss": null,
    "train/loss": 0.6271288871765137,
    "train/num_tokens": 12431985.0,
    "eval/samples_per_second": null
  },
  {
    "train/loss": 0.6245099067687988,
    "train/learning_rate": 9.912491572229366e-06,
    "eval/num_tokens": null,
    "eval/mean_token_accuracy": null,
    "train/epoch": 1.5878848063555115,
    "eval/entropy": null,
    "train/grad_norm": 0.0751953125,
    "eval/steps_per_second": null,
    "_runtime": 30926.410209461,
    "_timestamp": 1774097002.4190092,
    "train/mean_token_accuracy": 0.8604113966226578,
    "train/entropy": 0.6250055298209191,
    "train/global_step": 400,
    "eval/samples_per_second": null,
    "eval/loss": null,
    "eval/runtime": null,
    "train/num_tokens": 12590353.0,
    "_step": 81
  },
  {
    "train/num_tokens": null,
    "_runtime": 31212.133933045,
    "_timestamp": 1774097288.1429305,
    "eval/mean_token_accuracy": 0.8667885542989852,
    "train/loss": null,
    "train/global_step": 400,
    "eval/samples_per_second": 3.083,
    "eval/loss": 0.6051071286201477,
    "train/entropy": null,
    "train/grad_norm": null,
    "eval/steps_per_second": 0.388,
    "eval/entropy": 0.6027355556552475,
    "train/learning_rate": null,
    "_step": 82,
    "train/epoch": 1.5878848063555115,
    "train/mean_token_accuracy": null,
    "eval/runtime": 285.7222,
    "eval/num_tokens": 12590353.0
  },
  {
    "train/num_tokens": 12748441.0,
    "train/global_step": 405,
    "train/loss": 0.6191374301910401,
    "train/mean_token_accuracy": 0.862432324886322,
    "eval/num_tokens": null,
    "eval/samples_per_second": null,
    "train/entropy": 0.6227624982595443,
    "eval/runtime": null,
    "eval/steps_per_second": null,
    "_runtime": 31597.799505141,
    "_timestamp": 1774097673.8084087,
    "eval/mean_token_accuracy": null,
    "train/epoch": 1.6077457795431975,
    "eval/loss": null,
    "train/grad_norm": 0.0712890625,
    "eval/entropy": null,
    "train/learning_rate": 9.693764478583185e-06,
    "_step": 83
  },
  {
    "eval/samples_per_second": null,
    "_step": 84,
    "train/grad_norm": 0.0712890625,
    "eval/runtime": null,
    "train/global_step": 410,
    "_timestamp": 1774098056.5731695,
    "eval/entropy": null,
    "train/mean_token_accuracy": 0.8601124614477158,
    "train/entropy": 0.6373338773846626,
    "_runtime": 31980.564257053,
    "train/epoch": 1.627606752730884,
    "train/loss": 0.6318165779113769,
    "eval/num_tokens": null,
    "train/num_tokens": 12906323.0,
    "eval/steps_per_second": null,
    "eval/mean_token_accuracy": null,
    "eval/loss": null,
    "train/learning_rate": 9.475183949544204e-06
  },
  {
    "train/epoch": 1.64746772591857,
    "eval/loss": null,
    "eval/entropy": null,
    "eval/steps_per_second": null,
    "train/learning_rate": 9.256854597958222e-06,
    "eval/runtime": null,
    "train/num_tokens": 13064785.0,
    "eval/samples_per_second": null,
    "_runtime": 32366.936907383,
    "_timestamp": 1774098442.9456592,
    "eval/mean_token_accuracy": null,
    "train/mean_token_accuracy": 0.8658321231603623,
    "train/entropy": 0.6083572983741761,
    "_step": 85,
    "train/grad_norm": 0.0693359375,
    "train/loss": 0.6031959533691407,
    "train/global_step": 415,
    "eval/num_tokens": null
  },
  {
    "_runtime": 32749.76521813,
    "eval/entropy": null,
    "train/entropy": 0.6309187695384025,
    "train/epoch": 1.6673286991062564,
    "eval/samples_per_second": null,
    "_step": 86,
    "train/grad_norm": 0.06884765625,
    "eval/steps_per_second": null,
    "_timestamp": 1774098825.774062,
    "eval/mean_token_accuracy": null,
    "eval/loss": null,
    "train/learning_rate": 9.038880916457276e-06,
    "train/global_step": 420,
    "train/loss": 0.6304096221923828,
    "train/mean_token_accuracy": 0.8596030175685883,
    "eval/runtime": null,
    "train/num_tokens": 13222124.0,
    "eval/num_tokens": null
  },
  {
    "_timestamp": 1774099207.028093,
    "eval/runtime": null,
    "eval/num_tokens": null,
    "eval/samples_per_second": null,
    "eval/entropy": null,
    "train/loss": 0.6935991287231446,
    "train/entropy": 0.6934243783354759,
    "train/num_tokens": 13379078.0,
    "train/global_step": 425,
    "train/grad_norm": 0.07275390625,
    "eval/mean_token_accuracy": null,
    "train/mean_token_accuracy": 0.8485464334487915,
    "train/epoch": 1.6871896722939423,
    "eval/loss": null,
    "train/learning_rate": 8.821367227449368e-06,
    "_step": 87,
    "eval/steps_per_second": null,
    "_runtime": 33131.019174626
  },
  {
    "train/entropy": 0.5759698554873467,
    "eval/mean_token_accuracy": null,
    "train/epoch": 1.7070506454816285,
    "eval/entropy": null,
    "eval/samples_per_second": null,
    "eval/loss": null,
    "train/mean_token_accuracy": 0.8739586234092712,
    "eval/runtime": null,
    "train/global_step": 430,
    "train/grad_norm": 0.0673828125,
    "eval/steps_per_second": null,
    "_runtime": 33516.464647101,
    "_timestamp": 1774099592.473416,
    "train/loss": 0.5737429141998291,
    "train/learning_rate": 8.604417633189658e-06,
    "train/num_tokens": 13537015.0,
    "eval/num_tokens": null,
    "_step": 88
  },
  {
    "_runtime": 33899.03484929,
    "_timestamp": 1774099975.0436244,
    "eval/mean_token_accuracy": null,
    "eval/entropy": null,
    "train/mean_token_accuracy": 0.8606528252363205,
    "train/learning_rate": 8.388135965957031e-06,
    "train/entropy": 0.6279564753174782,
    "train/num_tokens": 13693922.0,
    "eval/num_tokens": null,
    "_step": 89,
    "train/grad_norm": 0.07177734375,
    "train/epoch": 1.7269116186693148,
    "train/loss": 0.6251816749572754,
    "eval/runtime": null,
    "train/global_step": 435,
    "eval/samples_per_second": null,
    "eval/steps_per_second": null,
    "eval/loss": null
  },
  {
    "eval/samples_per_second": null,
    "_step": 90,
    "eval/mean_token_accuracy": null,
    "train/loss": 0.6486200332641602,
    "train/entropy": 0.6552058696746826,
    "train/epoch": 1.746772591857001,
    "train/global_step": 440,
    "train/num_tokens": 13851482.0,
    "eval/steps_per_second": null,
    "_runtime": 34282.234694081,
    "_timestamp": 1774100358.2435377,
    "train/mean_token_accuracy": 0.855249461531639,
    "eval/runtime": null,
    "train/grad_norm": 0.0703125,
    "eval/loss": null,
    "eval/entropy": null,
    "train/learning_rate": 8.172625738359876e-06,
    "eval/num_tokens": null
  },
  {
    "eval/steps_per_second": null,
    "eval/runtime": null,
    "_step": 91,
    "_runtime": 34665.282292119,
    "train/mean_token_accuracy": 0.8710894733667374,
    "eval/samples_per_second": null,
    "train/grad_norm": 0.07275390625,
    "_timestamp": 1774100741.2911265,
    "eval/mean_token_accuracy": null,
    "eval/loss": null,
    "train/num_tokens": 14008926.0,
    "train/global_step": 445,
    "train/epoch": 1.7666335650446872,
    "eval/entropy": null,
    "train/loss": 0.5829760551452636,
    "train/learning_rate": 7.95799009379485e-06,
    "train/entropy": 0.5872889354825019,
    "eval/num_tokens": null
  },
  {
    "eval/steps_per_second": null,
    "_runtime": 35049.789410468,
    "train/mean_token_accuracy": 0.8746857106685638,
    "train/entropy": 0.5804151475429535,
    "eval/samples_per_second": null,
    "_step": 92,
    "_timestamp": 1774101125.7982337,
    "eval/loss": null,
    "train/loss": 0.5720758438110352,
    "train/learning_rate": 7.74433175708235e-06,
    "eval/runtime": null,
    "train/grad_norm": 0.0703125,
    "eval/mean_token_accuracy": null,
    "train/epoch": 1.7864945382323734,
    "train/num_tokens": 14167002.0,
    "train/global_step": 450,
    "eval/entropy": null,
    "eval/num_tokens": null
  },
  {
    "train/grad_norm": 0.0693359375,
    "eval/steps_per_second": null,
    "eval/loss": null,
    "train/loss": 0.6111544609069824,
    "train/entropy": 0.6145028814673423,
    "train/global_step": 455,
    "eval/num_tokens": null,
    "_timestamp": 1774101512.1745267,
    "eval/entropy": null,
    "train/learning_rate": 7.531752985302323e-06,
    "_runtime": 35436.165742288,
    "train/mean_token_accuracy": 0.8654966175556182,
    "_step": 93,
    "eval/mean_token_accuracy": null,
    "train/epoch": 1.8063555114200596,
    "eval/runtime": null,
    "train/num_tokens": 14325315.0,
    "eval/samples_per_second": null
  },
  {
    "train/epoch": 1.8262164846077458,
    "train/mean_token_accuracy": 0.8695839196443558,
    "train/entropy": 0.5823850512504578,
    "eval/runtime": null,
    "_step": 94,
    "train/loss": 0.5847176074981689,
    "eval/num_tokens": null,
    "eval/entropy": null,
    "train/global_step": 460,
    "eval/samples_per_second": null,
    "eval/steps_per_second": null,
    "_runtime": 35820.408356044,
    "eval/mean_token_accuracy": null,
    "eval/loss": null,
    "train/learning_rate": 7.320355518853921e-06,
    "train/num_tokens": 14483044.0,
    "train/grad_norm": 0.07275390625,
    "_timestamp": 1774101896.4171784
  },
  {
    "train/num_tokens": 14640810.0,
    "_timestamp": 1774102280.6229763,
    "eval/mean_token_accuracy": null,
    "train/epoch": 1.846077457795432,
    "train/entropy": 0.6078441724181175,
    "train/global_step": 465,
    "train/grad_norm": 0.06494140625,
    "_runtime": 36204.614177701,
    "eval/entropy": null,
    "train/loss": 0.6121020317077637,
    "train/mean_token_accuracy": 0.8648818165063858,
    "eval/runtime": null,
    "eval/num_tokens": null,
    "eval/samples_per_second": null,
    "_step": 95,
    "eval/steps_per_second": null,
    "eval/loss": null,
    "train/learning_rate": 7.110240532762469e-06
  },
  {
    "train/num_tokens": 14799044.0,
    "train/global_step": 470,
    "train/entropy": 0.5997092008590699,
    "eval/num_tokens": null,
    "eval/samples_per_second": null,
    "train/grad_norm": 0.06494140625,
    "_runtime": 36590.284586758,
    "_timestamp": 1774102666.2933664,
    "eval/mean_token_accuracy": null,
    "train/loss": 0.5973691463470459,
    "train/learning_rate": 6.9015085882569866e-06,
    "eval/runtime": null,
    "_step": 96,
    "train/epoch": 1.8659384309831182,
    "eval/loss": null,
    "eval/entropy": null,
    "train/mean_token_accuracy": 0.8671330958604813,
    "eval/steps_per_second": null
  },
  {
    "train/mean_token_accuracy": 0.8676124811172485,
    "train/entropy": 0.5974294006824493,
    "train/global_step": 475,
    "train/grad_norm": 0.07080078125,
    "_runtime": 36972.002237658,
    "_timestamp": 1774103048.0111353,
    "eval/loss": null,
    "eval/num_tokens": null,
    "train/epoch": 1.8857994041708044,
    "train/learning_rate": 6.694259584641496e-06,
    "eval/runtime": null,
    "eval/samples_per_second": null,
    "eval/steps_per_second": null,
    "eval/mean_token_accuracy": null,
    "eval/entropy": null,
    "train/num_tokens": 14956170.0,
    "_step": 97,
    "train/loss": 0.5909328937530518
  },
  {
    "train/num_tokens": 15114965.0,
    "train/grad_norm": 0.06640625,
    "eval/steps_per_second": null,
    "eval/mean_token_accuracy": null,
    "train/epoch": 1.9056603773584906,
    "eval/loss": null,
    "train/learning_rate": 6.488592711483122e-06,
    "_timestamp": 1774103435.6668184,
    "train/entropy": 0.6536797687411309,
    "eval/runtime": null,
    "eval/entropy": null,
    "train/loss": 0.6525641441345215,
    "train/global_step": 480,
    "_runtime": 37359.657990148,
    "train/mean_token_accuracy": 0.8561881333589554,
    "eval/num_tokens": null,
    "eval/samples_per_second": null,
    "_step": 98
  },
  {
    "eval/steps_per_second": null,
    "eval/entropy": null,
    "_step": 99,
    "_timestamp": 1774103814.6386385,
    "train/learning_rate": 6.284606401139875e-06,
    "train/entropy": 0.6226508930325508,
    "eval/runtime": null,
    "train/global_step": 485,
    "eval/samples_per_second": null,
    "train/grad_norm": 0.07177734375,
    "_runtime": 37738.629883041,
    "eval/mean_token_accuracy": null,
    "train/epoch": 1.9255213505461768,
    "train/mean_token_accuracy": 0.863499003648758,
    "train/num_tokens": 15271578.0,
    "eval/loss": null,
    "train/loss": 0.6161280632019043,
    "eval/num_tokens": null
  },
  {
    "_step": 100,
    "eval/entropy": null,
    "train/loss": 0.5766308784484864,
    "train/num_tokens": 15429716.0,
    "eval/num_tokens": null,
    "train/grad_norm": 0.08251953125,
    "train/mean_token_accuracy": 0.8719149112701416,
    "train/learning_rate": 6.082398281650823e-06,
    "eval/steps_per_second": null,
    "eval/mean_token_accuracy": null,
    "eval/loss": null,
    "train/entropy": 0.5765480011701584,
    "eval/runtime": null,
    "eval/samples_per_second": null,
    "_runtime": 38123.062424902,
    "_timestamp": 1774104199.0712545,
    "train/epoch": 1.945382323733863,
    "train/global_step": 490
  },
  {
    "eval/loss": null,
    "train/loss": 0.68623046875,
    "train/learning_rate": 5.882065130011226e-06,
    "eval/steps_per_second": null,
    "_runtime": 38500.271060843,
    "eval/entropy": null,
    "_timestamp": 1774104576.2798765,
    "train/entropy": 0.6827526301145553,
    "train/global_step": 495,
    "eval/num_tokens": null,
    "_step": 101,
    "train/mean_token_accuracy": 0.8508722096681595,
    "train/num_tokens": 15585908.0,
    "eval/samples_per_second": null,
    "eval/runtime": null,
    "train/grad_norm": 0.0751953125,
    "eval/mean_token_accuracy": null,
    "train/epoch": 1.9652432969215492
  },
  {
    "train/loss": 0.5881092548370361,
    "train/learning_rate": 5.68370282585499e-06,
    "eval/steps_per_second": null,
    "_timestamp": 1774104962.9048417,
    "eval/mean_token_accuracy": null,
    "eval/entropy": null,
    "train/mean_token_accuracy": 0.868158608675003,
    "eval/runtime": null,
    "train/num_tokens": 15744380.0,
    "train/global_step": 500,
    "train/epoch": 1.9851042701092354,
    "eval/loss": null,
    "eval/num_tokens": null,
    "eval/samples_per_second": null,
    "_step": 102,
    "train/grad_norm": 0.0693359375,
    "train/entropy": 0.5940338358283043,
    "_runtime": 38886.896099263
  },
  {
    "train/epoch": 2.0039721946375373,
    "eval/runtime": null,
    "eval/num_tokens": null,
    "eval/loss": null,
    "train/loss": 0.5881665229797364,
    "train/entropy": 0.5981959716269845,
    "train/global_step": 505,
    "_step": 103,
    "train/num_tokens": 15888702.0,
    "eval/steps_per_second": null,
    "eval/entropy": null,
    "train/mean_token_accuracy": 0.868668866784949,
    "train/grad_norm": 0.0693359375,
    "train/learning_rate": 5.4874063055665495e-06,
    "eval/samples_per_second": null,
    "_runtime": 39240.393393547,
    "_timestamp": 1774105316.402122,
    "eval/mean_token_accuracy": null
  },
  {
    "eval/mean_token_accuracy": null,
    "train/loss": 0.6249655246734619,
    "train/learning_rate": 5.293269516844263e-06,
    "train/entropy": 0.6244913130998612,
    "train/global_step": 510,
    "eval/num_tokens": null,
    "train/grad_norm": 0.06884765625,
    "train/mean_token_accuracy": 0.8619601607322693,
    "eval/samples_per_second": null,
    "_step": 104,
    "eval/steps_per_second": null,
    "train/epoch": 2.0238331678252233,
    "eval/loss": null,
    "eval/runtime": null,
    "train/num_tokens": 16046365.0,
    "eval/entropy": null,
    "_runtime": 39622.945127917,
    "_timestamp": 1774105698.9539814
  },
  {
    "train/loss": 0.6105315685272217,
    "eval/runtime": null,
    "eval/steps_per_second": null,
    "_runtime": 40005.480086229,
    "_step": 105,
    "train/grad_norm": 0.06787109375,
    "_timestamp": 1774106081.4889414,
    "eval/loss": null,
    "eval/entropy": null,
    "train/entropy": 0.6101155549287796,
    "train/num_tokens": 16203736.0,
    "train/global_step": 515,
    "eval/samples_per_second": null,
    "eval/mean_token_accuracy": null,
    "train/epoch": 2.0436941410129097,
    "train/mean_token_accuracy": 0.8641957461833953,
    "train/learning_rate": 5.101385373736937e-06,
    "eval/num_tokens": null
  },
  {
    "eval/entropy": null,
    "train/global_step": 520,
    "eval/samples_per_second": null,
    "eval/runtime": null,
    "train/num_tokens": 16361540.0,
    "_runtime": 40389.705968851,
    "train/loss": 0.5827394008636475,
    "train/learning_rate": 4.911845712175067e-06,
    "train/entropy": 0.5895358338952065,
    "eval/num_tokens": null,
    "eval/steps_per_second": null,
    "eval/mean_token_accuracy": null,
    "train/epoch": 2.0635551142005957,
    "train/grad_norm": 0.07177734375,
    "_timestamp": 1774106465.7147956,
    "eval/loss": null,
    "train/mean_token_accuracy": 0.8695755541324616,
    "_step": 106
  },
  {
    "eval/steps_per_second": null,
    "_timestamp": 1774106850.804486,
    "eval/entropy": null,
    "train/grad_norm": 0.07177734375,
    "train/entropy": 0.6516550153493881,
    "eval/runtime": null,
    "eval/num_tokens": null,
    "eval/mean_token_accuracy": null,
    "train/epoch": 2.083416087388282,
    "eval/loss": null,
    "train/loss": 0.6499483108520507,
    "train/global_step": 525,
    "_step": 107,
    "_runtime": 40774.795612817,
    "train/mean_token_accuracy": 0.8557853370904922,
    "train/learning_rate": 4.724741246018103e-06,
    "train/num_tokens": 16519350.0,
    "eval/samples_per_second": null
  },
  {
    "train/loss": 0.6538880348205567,
    "train/mean_token_accuracy": 0.8544500380754471,
    "eval/samples_per_second": null,
    "_step": 108,
    "_runtime": 41162.393247853,
    "eval/runtime": null,
    "train/global_step": 530,
    "eval/num_tokens": null,
    "eval/steps_per_second": null,
    "train/num_tokens": 16677977.0,
    "train/grad_norm": 0.07470703125,
    "_timestamp": 1774107238.4021673,
    "train/learning_rate": 4.5401615236386785e-06,
    "train/entropy": 0.6538953468203544,
    "eval/mean_token_accuracy": null,
    "train/epoch": 2.103277060575968,
    "eval/loss": null,
    "eval/entropy": null
  },
  {
    "train/num_tokens": 16834877.0,
    "eval/num_tokens": null,
    "eval/mean_token_accuracy": null,
    "eval/loss": null,
    "train/learning_rate": 4.358194885064704e-06,
    "eval/runtime": null,
    "train/global_step": 535,
    "_runtime": 41543.395985633,
    "_timestamp": 1774107619.4049275,
    "eval/samples_per_second": null,
    "_step": 109,
    "eval/steps_per_second": null,
    "train/epoch": 2.1231380337636545,
    "train/mean_token_accuracy": 0.868828734755516,
    "train/grad_norm": 0.072265625,
    "eval/entropy": null,
    "train/loss": 0.5882578372955323,
    "train/entropy": 0.5889563724398613
  },
  {
    "eval/steps_per_second": null,
    "eval/loss": null,
    "eval/entropy": null,
    "train/entropy": 0.6432792901992798,
    "eval/runtime": null,
    "_step": 110,
    "eval/mean_token_accuracy": null,
    "eval/samples_per_second": null,
    "_runtime": 41931.448754986,
    "_timestamp": 1774108007.4575522,
    "train/epoch": 2.1429990069513405,
    "train/loss": 0.6372509002685547,
    "train/learning_rate": 4.178928419699731e-06,
    "train/global_step": 540,
    "train/grad_norm": 0.0693359375,
    "train/mean_token_accuracy": 0.857935157418251,
    "train/num_tokens": 16993713.0,
    "eval/num_tokens": null
  },
  {
    "_step": 111,
    "eval/steps_per_second": null,
    "train/epoch": 2.162859980139027,
    "train/learning_rate": 4.002447924641882e-06,
    "eval/runtime": null,
    "eval/num_tokens": null,
    "eval/samples_per_second": null,
    "eval/mean_token_accuracy": null,
    "eval/loss": null,
    "eval/entropy": null,
    "train/num_tokens": 17151989.0,
    "train/grad_norm": 0.07373046875,
    "train/mean_token_accuracy": 0.8594664812088013,
    "_runtime": 42316.869227686,
    "_timestamp": 1774108392.8780468,
    "train/loss": 0.6282939910888672,
    "train/entropy": 0.6332933217287063,
    "train/global_step": 545
  },
  {
    "train/epoch": 2.182720953326713,
    "train/global_step": 550,
    "eval/num_tokens": null,
    "eval/runtime": null,
    "train/num_tokens": 17308748.0,
    "_timestamp": 1774108773.3530965,
    "eval/mean_token_accuracy": null,
    "eval/loss": null,
    "train/loss": 0.5935729026794434,
    "train/entropy": 0.5973384410142899,
    "train/grad_norm": 0.0712890625,
    "_runtime": 42697.344298463,
    "eval/entropy": null,
    "eval/samples_per_second": null,
    "_step": 112,
    "eval/steps_per_second": null,
    "train/mean_token_accuracy": 0.8682833582162857,
    "train/learning_rate": 3.828837863621286e-06
  },
  {
    "_step": 113,
    "train/grad_norm": 0.06884765625,
    "_runtime": 43080.971605887,
    "eval/mean_token_accuracy": null,
    "train/mean_token_accuracy": 0.8648058712482453,
    "train/num_tokens": 17466480.0,
    "eval/samples_per_second": null,
    "eval/loss": null,
    "_timestamp": 1774109156.980489,
    "train/epoch": 2.2025819265143993,
    "eval/entropy": null,
    "train/loss": 0.6010529041290283,
    "train/entropy": 0.6112238019704819,
    "eval/num_tokens": null,
    "eval/steps_per_second": null,
    "train/learning_rate": 3.6581813265756595e-06,
    "eval/runtime": null,
    "train/global_step": 555
  },
  {
    "train/mean_token_accuracy": 0.8703880786895752,
    "train/learning_rate": 3.4905599898833665e-06,
    "_step": 114,
    "_timestamp": 1774109541.3501642,
    "train/epoch": 2.2224428997020853,
    "train/loss": 0.5785223007202148,
    "eval/runtime": null,
    "train/num_tokens": 17624461.0,
    "train/global_step": 560,
    "eval/samples_per_second": null,
    "_runtime": 43465.341302717,
    "eval/loss": null,
    "train/grad_norm": 0.0693359375,
    "eval/steps_per_second": null,
    "eval/mean_token_accuracy": null,
    "eval/entropy": null,
    "train/entropy": 0.5841721221804619,
    "eval/num_tokens": null
  },
  {
    "eval/mean_token_accuracy": null,
    "eval/entropy": null,
    "train/mean_token_accuracy": 0.8710242718458175,
    "train/entropy": 0.5902263298630714,
    "train/grad_norm": 0.0703125,
    "eval/steps_per_second": null,
    "_timestamp": 1774109926.2699568,
    "train/epoch": 2.2423038728897717,
    "train/loss": 0.5862852096557617,
    "train/learning_rate": 3.3260540772730576e-06,
    "train/num_tokens": 17782441.0,
    "train/global_step": 565,
    "eval/samples_per_second": null,
    "_runtime": 43850.261197322,
    "eval/loss": null,
    "eval/runtime": null,
    "eval/num_tokens": null,
    "_step": 115
  },
  {
    "train/grad_norm": 0.072265625,
    "_runtime": 44232.884088803,
    "train/learning_rate": 3.1647423214284856e-06,
    "train/num_tokens": 17939858.0,
    "train/global_step": 570,
    "eval/steps_per_second": null,
    "_timestamp": 1774110308.8930047,
    "eval/mean_token_accuracy": null,
    "train/epoch": 2.2621648460774577,
    "train/loss": 0.600101900100708,
    "train/entropy": 0.6026528939604759,
    "eval/runtime": null,
    "eval/num_tokens": null,
    "eval/loss": null,
    "eval/entropy": null,
    "eval/samples_per_second": null,
    "train/mean_token_accuracy": 0.8674422144889832,
    "_step": 116
  },
  {
    "eval/samples_per_second": null,
    "eval/steps_per_second": null,
    "eval/loss": null,
    "eval/entropy": null,
    "_step": 117,
    "_timestamp": 1774110690.0579002,
    "train/loss": 0.623255729675293,
    "train/learning_rate": 3.0067019263069973e-06,
    "train/grad_norm": 0.07470703125,
    "eval/mean_token_accuracy": null,
    "train/entropy": 0.6259896546602249,
    "eval/runtime": null,
    "train/global_step": 575,
    "_runtime": 44614.04909523,
    "train/epoch": 2.282025819265144,
    "train/mean_token_accuracy": 0.8613677829504013,
    "train/num_tokens": 18096931.0,
    "eval/num_tokens": null
  },
  {
    "train/num_tokens": 18255449.0,
    "_timestamp": 1774111077.985721,
    "eval/mean_token_accuracy": null,
    "train/mean_token_accuracy": 0.8497486293315888,
    "train/learning_rate": 2.8520085301896373e-06,
    "eval/runtime": null,
    "eval/num_tokens": null,
    "eval/samples_per_second": null,
    "eval/steps_per_second": null,
    "_runtime": 45001.97695666,
    "eval/loss": null,
    "train/global_step": 580,
    "_step": 118,
    "train/grad_norm": 0.07177734375,
    "train/epoch": 2.30188679245283,
    "train/loss": 0.6677382469177247,
    "eval/entropy": null,
    "train/entropy": 0.6740051299333573
  },
  {
    "eval/steps_per_second": null,
    "eval/mean_token_accuracy": null,
    "train/mean_token_accuracy": 0.8677396714687348,
    "eval/runtime": null,
    "train/global_step": 585,
    "eval/samples_per_second": null,
    "_step": 119,
    "_runtime": 45385.6958848,
    "train/epoch": 2.3217477656405165,
    "train/learning_rate": 2.7007361694805735e-06,
    "train/entropy": 0.5969226852059364,
    "train/num_tokens": 18413168.0,
    "_timestamp": 1774111461.7046788,
    "eval/loss": null,
    "eval/entropy": null,
    "train/loss": 0.5958587646484375,
    "eval/num_tokens": null,
    "train/grad_norm": 0.06884765625
  },
  {
    "train/loss": 0.6605926036834717,
    "train/grad_norm": 0.068359375,
    "eval/loss": null,
    "train/mean_token_accuracy": 0.8536922723054886,
    "train/entropy": 0.660072599351406,
    "train/global_step": 590,
    "eval/num_tokens": null,
    "eval/samples_per_second": null,
    "train/learning_rate": 2.5529572432732473e-06,
    "train/num_tokens": 18571577.0,
    "_timestamp": 1774111849.188505,
    "eval/entropy": null,
    "eval/runtime": null,
    "_step": 120,
    "eval/steps_per_second": null,
    "_runtime": 45773.179588302,
    "eval/mean_token_accuracy": null,
    "train/epoch": 2.3416087388282025
  },
  {
    "_runtime": 46156.865203161,
    "train/mean_token_accuracy": 0.8697842925786972,
    "train/global_step": 595,
    "eval/num_tokens": null,
    "eval/mean_token_accuracy": null,
    "train/epoch": 2.361469712015889,
    "eval/loss": null,
    "train/num_tokens": 18729272.0,
    "_step": 121,
    "train/grad_norm": 0.07080078125,
    "eval/steps_per_second": null,
    "eval/entropy": null,
    "train/learning_rate": 2.408742478700071e-06,
    "train/entropy": 0.584681449830532,
    "eval/runtime": null,
    "eval/samples_per_second": null,
    "_timestamp": 1774112232.8740752,
    "train/loss": 0.5850774765014648
  },
  {
    "train/grad_norm": 0.06640625,
    "eval/steps_per_second": null,
    "eval/mean_token_accuracy": null,
    "train/mean_token_accuracy": 0.8849996984004974,
    "_runtime": 46538.175261267,
    "eval/entropy": null,
    "train/loss": 0.5203165531158447,
    "train/global_step": 600,
    "_timestamp": 1774112614.1840272,
    "eval/runtime": null,
    "train/num_tokens": 18886260.0,
    "train/epoch": 2.381330685203575,
    "eval/loss": null,
    "train/learning_rate": 2.2681608970823567e-06,
    "train/entropy": 0.5273639544844627,
    "eval/num_tokens": null,
    "eval/samples_per_second": null,
    "_step": 122
  },
  {
    "_timestamp": 1774112899.7491114,
    "eval/loss": 0.5978290438652039,
    "train/grad_norm": null,
    "_runtime": 46823.740151527,
    "eval/mean_token_accuracy": 0.8679558264242636,
    "train/epoch": 2.381330685203575,
    "train/mean_token_accuracy": null,
    "train/global_step": 600,
    "_step": 123,
    "eval/steps_per_second": 0.389,
    "eval/entropy": 0.5932364474545728,
    "train/learning_rate": null,
    "train/entropy": null,
    "eval/num_tokens": 18886260.0,
    "eval/samples_per_second": 3.085,
    "train/loss": null,
    "eval/runtime": 285.5637,
    "train/num_tokens": null
  },
  {
    "_timestamp": 1774113290.429483,
    "train/epoch": 2.4011916583912614,
    "train/num_tokens": 19045204.0,
    "train/global_step": 605,
    "eval/steps_per_second": null,
    "eval/entropy": null,
    "train/loss": 0.6193355083465576,
    "train/mean_token_accuracy": 0.8624697148799896,
    "train/entropy": 0.6200324758887291,
    "train/grad_norm": 0.0673828125,
    "_runtime": 47214.420564818,
    "eval/mean_token_accuracy": null,
    "train/learning_rate": 2.1312797808966625e-06,
    "eval/num_tokens": null,
    "eval/samples_per_second": null,
    "_step": 124,
    "eval/loss": null,
    "eval/runtime": null
  },
  {
    "eval/runtime": null,
    "eval/entropy": null,
    "train/num_tokens": 19203578.0,
    "eval/num_tokens": null,
    "eval/samples_per_second": null,
    "train/grad_norm": 0.0712890625,
    "eval/steps_per_second": null,
    "_timestamp": 1774113677.301581,
    "eval/mean_token_accuracy": null,
    "train/mean_token_accuracy": 0.8650276452302933,
    "_step": 125,
    "_runtime": 47601.292821995,
    "eval/loss": null,
    "train/loss": 0.6080891132354737,
    "train/learning_rate": 1.9981646415733157e-06,
    "train/entropy": 0.6058387786149979,
    "train/global_step": 610,
    "train/epoch": 2.4210526315789473
  },
  {
    "eval/entropy": null,
    "train/loss": 0.584065055847168,
    "eval/steps_per_second": null,
    "eval/mean_token_accuracy": null,
    "train/learning_rate": 1.8688791881426017e-06,
    "train/entropy": 0.5883324116468429,
    "eval/runtime": null,
    "eval/samples_per_second": null,
    "_step": 126,
    "train/mean_token_accuracy": 0.8700357586145401,
    "eval/num_tokens": null,
    "train/epoch": 2.4409136047666333,
    "eval/loss": null,
    "train/num_tokens": 19361477.0,
    "train/global_step": 615,
    "train/grad_norm": 0.07080078125,
    "_runtime": 47986.517577149,
    "_timestamp": 1774114062.5263453
  },
  {
    "train/grad_norm": 0.06787109375,
    "_runtime": 48373.271708946,
    "train/epoch": 2.4607745779543198,
    "eval/loss": null,
    "train/mean_token_accuracy": 0.8602054446935654,
    "_timestamp": 1774114449.2805274,
    "train/num_tokens": 19519836.0,
    "eval/num_tokens": null,
    "eval/steps_per_second": null,
    "eval/mean_token_accuracy": null,
    "train/loss": 0.6313722610473633,
    "train/entropy": 0.6353312686085701,
    "eval/runtime": null,
    "train/global_step": 620,
    "eval/samples_per_second": null,
    "_step": 127,
    "eval/entropy": null,
    "train/learning_rate": 1.7434852967435523e-06
  },
  {
    "eval/loss": null,
    "eval/entropy": null,
    "train/mean_token_accuracy": 0.8526807397603988,
    "train/learning_rate": 1.6220429810099603e-06,
    "train/num_tokens": 19678141.0,
    "train/grad_norm": 0.0712890625,
    "train/epoch": 2.480635551142006,
    "eval/runtime": null,
    "train/global_step": 625,
    "eval/samples_per_second": null,
    "train/entropy": 0.666301691532135,
    "_step": 128,
    "eval/steps_per_second": null,
    "_runtime": 48760.317373763,
    "eval/mean_token_accuracy": null,
    "train/loss": 0.6654084205627442,
    "eval/num_tokens": null,
    "_timestamp": 1774114836.3262787
  },
  {
    "train/num_tokens": 19835166.0,
    "train/grad_norm": 0.06787109375,
    "_timestamp": 1774115218.733976,
    "eval/loss": null,
    "train/global_step": 630,
    "_step": 129,
    "train/epoch": 2.500496524329692,
    "train/loss": 0.6137460231781006,
    "train/mean_token_accuracy": 0.8655975997447968,
    "train/learning_rate": 1.5046103633478148e-06,
    "eval/samples_per_second": null,
    "eval/steps_per_second": null,
    "eval/runtime": null,
    "eval/num_tokens": null,
    "_runtime": 49142.725157789,
    "eval/mean_token_accuracy": null,
    "eval/entropy": null,
    "train/entropy": 0.6175593137741089
  },
  {
    "train/grad_norm": 0.07421875,
    "eval/steps_per_second": null,
    "train/mean_token_accuracy": 0.8676866561174392,
    "train/learning_rate": 1.3912436471178525e-06,
    "eval/runtime": null,
    "train/num_tokens": 19992354.0,
    "eval/num_tokens": null,
    "_runtime": 49525.513294985,
    "train/epoch": 2.520357497517378,
    "train/loss": 0.5956701278686524,
    "train/entropy": 0.5994615644216538,
    "_timestamp": 1774115601.5221431,
    "eval/samples_per_second": null,
    "_step": 130,
    "eval/mean_token_accuracy": null,
    "eval/loss": null,
    "eval/entropy": null,
    "train/global_step": 635
  },
  {
    "eval/steps_per_second": null,
    "_runtime": 49908.855167878,
    "train/global_step": 640,
    "_step": 131,
    "eval/mean_token_accuracy": null,
    "train/mean_token_accuracy": 0.8657822012901306,
    "train/learning_rate": 1.281997089736574e-06,
    "eval/runtime": null,
    "train/num_tokens": 20149736.0,
    "eval/num_tokens": null,
    "_timestamp": 1774115984.863905,
    "train/epoch": 2.5402184707050646,
    "eval/loss": null,
    "train/loss": 0.6072444915771484,
    "eval/samples_per_second": null,
    "train/grad_norm": 0.0703125,
    "eval/entropy": null,
    "train/entropy": 0.6078303992748261
  },
  {
    "train/grad_norm": 0.07470703125,
    "eval/entropy": null,
    "train/mean_token_accuracy": 0.8509427547454834,
    "train/learning_rate": 1.1769229767086053e-06,
    "eval/num_tokens": null,
    "eval/samples_per_second": null,
    "eval/steps_per_second": null,
    "_timestamp": 1774116369.2040956,
    "eval/mean_token_accuracy": null,
    "eval/runtime": null,
    "train/global_step": 645,
    "_step": 132,
    "_runtime": 50293.195183439,
    "train/epoch": 2.560079443892751,
    "eval/loss": null,
    "train/loss": 0.6681599617004395,
    "train/entropy": 0.6750094890594482,
    "train/num_tokens": 20307249.0
  },
  {
    "_timestamp": 1774116751.2944446,
    "eval/mean_token_accuracy": null,
    "eval/entropy": null,
    "train/loss": 0.6301857948303222,
    "train/learning_rate": 1.0760715966027923e-06,
    "eval/samples_per_second": null,
    "_step": 133,
    "train/grad_norm": 0.07373046875,
    "eval/loss": null,
    "train/mean_token_accuracy": 0.8608615279197693,
    "_runtime": 50675.285511738,
    "train/epoch": 2.579940417080437,
    "train/entropy": 0.6335357755422593,
    "train/num_tokens": 20464214.0,
    "eval/num_tokens": null,
    "eval/runtime": null,
    "train/global_step": 650,
    "eval/steps_per_second": null
  },
  {
    "train/learning_rate": 9.794912169840564e-07,
    "eval/runtime": null,
    "_runtime": 51058.303750598,
    "train/global_step": 655,
    "eval/samples_per_second": null,
    "train/num_tokens": 20621397.0,
    "_timestamp": 1774117134.3125567,
    "eval/entropy": null,
    "train/mean_token_accuracy": 0.8650037050247192,
    "eval/num_tokens": null,
    "_step": 134,
    "eval/mean_token_accuracy": null,
    "eval/loss": null,
    "train/loss": 0.5984361648559571,
    "train/entropy": 0.6031161174178123,
    "train/grad_norm": 0.0732421875,
    "eval/steps_per_second": null,
    "train/epoch": 2.599801390268123
  },
  {
    "_timestamp": 1774117519.815564,
    "train/epoch": 2.6196623634558094,
    "train/mean_token_accuracy": 0.8652630984783173,
    "train/learning_rate": 8.872280613124895e-07,
    "eval/num_tokens": null,
    "eval/samples_per_second": null,
    "_step": 135,
    "eval/loss": null,
    "_runtime": 51443.806759761,
    "eval/entropy": null,
    "train/loss": 0.6027578353881836,
    "train/entropy": 0.6087049514055252,
    "eval/runtime": null,
    "train/num_tokens": 20779314.0,
    "train/global_step": 660,
    "train/grad_norm": 0.06591796875,
    "eval/steps_per_second": null,
    "eval/mean_token_accuracy": null
  },
  {
    "eval/steps_per_second": null,
    "train/loss": 0.622073745727539,
    "train/learning_rate": 7.993262868207552e-07,
    "eval/runtime": null,
    "eval/samples_per_second": null,
    "eval/entropy": null,
    "train/entropy": 0.6337837010622025,
    "eval/num_tokens": null,
    "_runtime": 51829.616166379,
    "_timestamp": 1774117905.6249344,
    "eval/mean_token_accuracy": null,
    "train/grad_norm": 0.0654296875,
    "train/epoch": 2.6395233366434954,
    "eval/loss": null,
    "train/mean_token_accuracy": 0.8616469204425812,
    "train/num_tokens": 20937382.0,
    "train/global_step": 665,
    "_step": 136
  },
  {
    "eval/steps_per_second": null,
    "_runtime": 52210.500341744,
    "train/epoch": 2.659384309831182,
    "train/mean_token_accuracy": 0.866363400220871,
    "train/learning_rate": 7.158279633804077e-07,
    "train/entropy": 0.6036852493882179,
    "train/num_tokens": 21093688.0,
    "train/global_step": 670,
    "_timestamp": 1774118286.5091035,
    "eval/entropy": null,
    "eval/samples_per_second": null,
    "_step": 137,
    "eval/runtime": null,
    "train/grad_norm": 0.0732421875,
    "eval/mean_token_accuracy": null,
    "eval/loss": null,
    "train/loss": 0.6002536296844483,
    "eval/num_tokens": null
  },
  {
    "_runtime": 52595.31538314,
    "eval/runtime": null,
    "train/num_tokens": 21251598.0,
    "train/global_step": 675,
    "eval/samples_per_second": null,
    "train/grad_norm": 0.068359375,
    "train/learning_rate": 6.367730533672035e-07,
    "eval/steps_per_second": null,
    "eval/mean_token_accuracy": null,
    "eval/loss": null,
    "eval/entropy": null,
    "train/loss": 0.6570178031921386,
    "eval/num_tokens": null,
    "_step": 138,
    "_timestamp": 1774118671.3242245,
    "train/epoch": 2.6792452830188678,
    "train/mean_token_accuracy": 0.8544352233409882,
    "train/entropy": 0.6597185268998146
  },
  {
    "train/global_step": 680,
    "eval/num_tokens": null,
    "_step": 139,
    "_runtime": 52981.622647216,
    "train/loss": 0.6576930999755859,
    "train/learning_rate": 5.621993925350722e-07,
    "eval/runtime": null,
    "eval/samples_per_second": null,
    "eval/steps_per_second": null,
    "eval/mean_token_accuracy": null,
    "train/epoch": 2.699106256206554,
    "eval/entropy": null,
    "train/mean_token_accuracy": 0.8532999575138092,
    "train/grad_norm": 0.0751953125,
    "_timestamp": 1774119057.6314545,
    "eval/loss": null,
    "train/entropy": 0.6599578812718392,
    "train/num_tokens": 21409472.0
  },
  {
    "train/entropy": 0.6070284113287926,
    "train/num_tokens": 21564593.0,
    "_runtime": 53357.40651049,
    "eval/loss": null,
    "eval/entropy": null,
    "eval/runtime": null,
    "_step": 140,
    "train/loss": 0.6044232368469238,
    "eval/num_tokens": null,
    "eval/samples_per_second": null,
    "train/grad_norm": 0.07275390625,
    "eval/mean_token_accuracy": null,
    "train/learning_rate": 4.921426719078948e-07,
    "train/global_step": 685,
    "eval/steps_per_second": null,
    "_timestamp": 1774119433.41533,
    "train/epoch": 2.71896722939424,
    "train/mean_token_accuracy": 0.8677282899618148
  },
  {
    "eval/mean_token_accuracy": null,
    "train/learning_rate": 4.2663642069773693e-07,
    "train/num_tokens": 21721033.0,
    "train/global_step": 690,
    "train/grad_norm": 0.07373046875,
    "train/epoch": 2.7388282025819266,
    "train/loss": 0.6037854194641114,
    "eval/num_tokens": null,
    "eval/samples_per_second": null,
    "eval/entropy": null,
    "train/entropy": 0.6073181509971619,
    "eval/runtime": null,
    "eval/steps_per_second": null,
    "eval/loss": null,
    "train/mean_token_accuracy": 0.8664025634527206,
    "_step": 141,
    "_runtime": 53737.30818729,
    "_timestamp": 1774119813.3170414
  },
  {
    "train/entropy": 0.6019581288099289,
    "train/num_tokens": 21879160.0,
    "eval/samples_per_second": null,
    "eval/steps_per_second": null,
    "_timestamp": 1774120200.2922547,
    "eval/loss": null,
    "train/learning_rate": 3.657119902577466e-07,
    "eval/runtime": null,
    "eval/num_tokens": null,
    "eval/mean_token_accuracy": null,
    "train/epoch": 2.7586891757696126,
    "eval/entropy": null,
    "train/loss": 0.5986729145050049,
    "train/global_step": 695,
    "_step": 142,
    "train/grad_norm": 0.07080078125,
    "_runtime": 54124.283457799,
    "train/mean_token_accuracy": 0.8686566680669785
  },
  {
    "eval/steps_per_second": null,
    "train/learning_rate": 3.0939853907736126e-07,
    "eval/runtime": null,
    "_step": 143,
    "train/grad_norm": 0.068359375,
    "_timestamp": 1774120586.3251276,
    "train/epoch": 2.778550148957299,
    "eval/entropy": null,
    "train/loss": 0.5915535926818848,
    "train/mean_token_accuracy": 0.8685595273971558,
    "train/entropy": 0.5951066628098488,
    "_runtime": 54510.31630078,
    "eval/loss": null,
    "eval/num_tokens": null,
    "eval/samples_per_second": null,
    "train/num_tokens": 22037490.0,
    "eval/mean_token_accuracy": null,
    "train/global_step": 700
  },
  {
    "train/grad_norm": 0.0673828125,
    "eval/mean_token_accuracy": null,
    "eval/loss": null,
    "train/learning_rate": 2.5772301882702634e-07,
    "eval/runtime": null,
    "train/num_tokens": 22195238.0,
    "eval/num_tokens": null,
    "eval/samples_per_second": null,
    "train/epoch": 2.798411122144985,
    "eval/entropy": null,
    "train/loss": 0.5806747913360596,
    "_step": 144,
    "_runtime": 54894.907267076,
    "eval/steps_per_second": null,
    "_timestamp": 1774120970.9161873,
    "train/mean_token_accuracy": 0.871490341424942,
    "train/entropy": 0.5839985236525536,
    "train/global_step": 705
  },
  {
    "_runtime": 55278.07230772,
    "eval/mean_token_accuracy": null,
    "eval/runtime": null,
    "train/num_tokens": 22352387.0,
    "eval/num_tokens": null,
    "eval/samples_per_second": null,
    "train/global_step": 710,
    "_step": 145,
    "train/grad_norm": 0.06982421875,
    "train/epoch": 2.8182720953326714,
    "eval/loss": null,
    "eval/entropy": null,
    "train/loss": 0.5704697608947754,
    "eval/steps_per_second": null,
    "_timestamp": 1774121354.0811424,
    "train/mean_token_accuracy": 0.8743905544281005,
    "train/learning_rate": 2.107101614591045e-07,
    "train/entropy": 0.5705913245677948
  },
  {
    "train/loss": 0.6423473358154297,
    "_timestamp": 1774121737.3908238,
    "train/epoch": 2.8381330685203574,
    "train/mean_token_accuracy": 0.8574590593576431,
    "train/learning_rate": 1.6838246737113983e-07,
    "train/entropy": 0.6413764253258705,
    "eval/runtime": null,
    "eval/samples_per_second": null,
    "eval/steps_per_second": null,
    "eval/loss": null,
    "train/num_tokens": 22509648.0,
    "eval/num_tokens": null,
    "train/grad_norm": 0.0712890625,
    "eval/mean_token_accuracy": null,
    "train/global_step": 715,
    "_step": 146,
    "_runtime": 55661.382023021,
    "eval/entropy": null
  },
  {
    "eval/steps_per_second": null,
    "_runtime": 56049.256757447,
    "_timestamp": 1774122125.2656322,
    "train/global_step": 720,
    "eval/samples_per_second": null,
    "train/grad_norm": 0.0732421875,
    "train/learning_rate": 1.3076019463714173e-07,
    "train/entropy": 0.6448058769106865,
    "eval/runtime": null,
    "train/num_tokens": 22668146.0,
    "eval/num_tokens": null,
    "train/epoch": 2.857994041708044,
    "eval/entropy": null,
    "train/mean_token_accuracy": 0.8575087159872055,
    "_step": 147,
    "eval/mean_token_accuracy": null,
    "eval/loss": null,
    "train/loss": 0.6431620121002197
  },
  {
    "train/mean_token_accuracy": 0.8634161204099655,
    "train/entropy": 0.6168686658143997,
    "train/num_tokens": 22826222.0,
    "eval/num_tokens": null,
    "eval/steps_per_second": null,
    "eval/loss": null,
    "train/learning_rate": 9.786134931205726e-08,
    "eval/mean_token_accuracy": null,
    "train/epoch": 2.87785501489573,
    "eval/entropy": null,
    "eval/runtime": null,
    "_step": 148,
    "train/grad_norm": 0.068359375,
    "_runtime": 56435.355845815,
    "_timestamp": 1774122511.364801,
    "train/loss": 0.6112209796905518,
    "train/global_step": 725,
    "eval/samples_per_second": null
  },
  {
    "train/num_tokens": 22982911.0,
    "train/grad_norm": 0.072265625,
    "eval/loss": null,
    "eval/entropy": null,
    "eval/runtime": null,
    "train/global_step": 730,
    "eval/num_tokens": null,
    "_runtime": 56816.48750976,
    "train/epoch": 2.8977159880834162,
    "train/mean_token_accuracy": 0.8720939368009567,
    "eval/samples_per_second": null,
    "train/learning_rate": 6.970167681405459e-08,
    "train/entropy": 0.5792048454284668,
    "_step": 149,
    "eval/steps_per_second": null,
    "_timestamp": 1774122892.4964209,
    "eval/mean_token_accuracy": null,
    "train/loss": 0.5795931816101074
  },
  {
    "train/num_tokens": 23139133.0,
    "_timestamp": 1774123271.4222546,
    "eval/entropy": null,
    "eval/num_tokens": null,
    "eval/steps_per_second": null,
    "eval/loss": null,
    "train/loss": 0.5705300807952881,
    "eval/runtime": null,
    "_step": 150,
    "train/grad_norm": 0.068359375,
    "_runtime": 57195.413426203,
    "train/epoch": 2.917576961271102,
    "train/mean_token_accuracy": 0.873980587720871,
    "train/learning_rate": 4.62946543887488e-08,
    "train/entropy": 0.5708086967468262,
    "train/global_step": 735,
    "eval/samples_per_second": null,
    "eval/mean_token_accuracy": null
  },
  {
    "train/grad_norm": 0.07080078125,
    "train/entropy": 0.6658387899398803,
    "eval/runtime": null,
    "eval/num_tokens": null,
    "eval/steps_per_second": null,
    "train/epoch": 2.9374379344587886,
    "eval/entropy": null,
    "train/learning_rate": 2.7651484658984816e-08,
    "_timestamp": 1774123654.6765974,
    "eval/mean_token_accuracy": null,
    "eval/loss": null,
    "train/num_tokens": 23296529.0,
    "train/global_step": 740,
    "eval/samples_per_second": null,
    "_step": 151,
    "_runtime": 57578.667827285,
    "train/loss": 0.6637350082397461,
    "train/mean_token_accuracy": 0.8524390965700149
  },
  {
    "eval/mean_token_accuracy": null,
    "_step": 152,
    "train/grad_norm": 0.06884765625,
    "_runtime": 57959.667505256,
    "eval/entropy": null,
    "train/mean_token_accuracy": 0.8634848058223724,
    "train/global_step": 745,
    "_timestamp": 1774124035.676291,
    "train/epoch": 2.9572989076464746,
    "train/loss": 0.6179518699645996,
    "train/learning_rate": 1.3781090263242924e-08,
    "train/entropy": 0.624837777018547,
    "eval/runtime": null,
    "train/num_tokens": 23453214.0,
    "eval/num_tokens": null,
    "eval/steps_per_second": null,
    "eval/loss": null,
    "eval/samples_per_second": null
  },
  {
    "eval/entropy": null,
    "train/global_step": 750,
    "train/grad_norm": 0.0693359375,
    "_runtime": 58340.511558582,
    "eval/mean_token_accuracy": null,
    "train/learning_rate": 4.690109585268054e-09,
    "eval/runtime": null,
    "eval/num_tokens": null,
    "_timestamp": 1774124416.5203183,
    "train/loss": 0.5654942512512207,
    "train/mean_token_accuracy": 0.875880452990532,
    "train/entropy": 0.5718929976224899,
    "eval/samples_per_second": null,
    "_step": 153,
    "train/num_tokens": 23609944.0,
    "eval/steps_per_second": null,
    "train/epoch": 2.9771598808341606,
    "eval/loss": null
  },
  {
    "train/mean_token_accuracy": 0.8538794487714767,
    "eval/loss": null,
    "train/global_step": 755,
    "_step": 154,
    "train/entropy": 0.6643248975276947,
    "train/num_tokens": 23768737.0,
    "eval/steps_per_second": null,
    "_runtime": 58729.282503258,
    "train/loss": 0.6610596179962158,
    "eval/num_tokens": null,
    "eval/entropy": null,
    "eval/samples_per_second": null,
    "train/learning_rate": 3.8289357691900785e-10,
    "eval/runtime": null,
    "train/grad_norm": 0.0712890625,
    "_timestamp": 1774124805.2912488,
    "eval/mean_token_accuracy": null,
    "train/epoch": 2.997020854021847
  },
  {
    "train/num_tokens": 23785407.0,
    "train/grad_norm": null,
    "eval/mean_token_accuracy": null,
    "train/epoch": 3,
    "train/learning_rate": null,
    "train/entropy": 0.9612506628036499,
    "eval/samples_per_second": null,
    "_step": 155,
    "eval/loss": null,
    "train/mean_token_accuracy": 0.7808510462443033,
    "train/global_step": 756,
    "eval/num_tokens": null,
    "_runtime": 58770.155122168,
    "train/loss": null,
    "eval/runtime": null,
    "eval/steps_per_second": null,
    "_timestamp": 1774124846.1641436,
    "eval/entropy": null
  }
]